Workbook

Sheet HO,A.A SHOP
A1: LeapFrog Software Technology Africa PLC
A2: Payroll Sheet Head office and A.A shop
A3: For the Month of June 2026/Sene 2018
A5: No. | B5: Name of Employees | C5: Position | D5: Shop Name | E5: Working days | F5: Basic Salary | G5: Monthly Salary | H5: Commiss. /OT | I5: KPI | J5: Gross Salary | K5: Taxable Income | L5: Income Tax | M5: Pension 7% | N5: Pension 11% | O5: Shortage/ Loan | P5: Total Deduction | Q5: Transport & other allowance | R5: Net Pay | S5: sign
A6: 1 | B6: Abaynesh Abera | C6: Cleaner | D6: 4KILO | E6: 30 | F6: 3695.2 | G6: =+F6/30*E6 -> 3695.2 | J6: =G6+H6+I6 -> 3695.2 | K6: =G6+H6+I6 -> 3695.2 | L6: =IF(K6<=2000,(0),IF(K6<=4000,(K6*0.15)-300,IF(K6<=7000,(K6*0.2)-500,IF(K6<=10000,(K6*0.25)-850,IF(K6<=14000,(K6*0.3)-1350,IF(K6>14000,(K6*0.35)-2050)))))) -> 254.28 | M6: =F6*0.07 -> 258.664 | N6: =F6*0.11 -> 406.472 | P6: =L6+M6+O6 -> 512.944 | R6: =J6-P6+Q6 -> 3182.256
A7: 2 | B7: Abebu Shumye | C7: Cleaner | D7: BoleArabsa | E7: 30 | F7: 2179.49 | G7: =+F7/30*E7 -> 2179.49 | J7: =G7+H7+I7 -> 2179.49 | K7: =G7+H7+I7 -> 2179.49 | L7: =IF(K7<=2000,(0),IF(K7<=4000,(K7*0.15)-300,IF(K7<=7000,(K7*0.2)-500,IF(K7<=10000,(K7*0.25)-850,IF(K7<=14000,(K7*0.3)-1350,IF(K7>14000,(K7*0.35)-2050)))))) -> 26.9235 | M7: =F7*0.07 -> 152.5643 | N7: =F7*0.11 -> 239.7439 | P7: =L7+M7+O7 -> 179.4878 | R7: =J7-P7+Q7 -> 2000.0022
A8: 3 | B8: Abel Gezahegn | C8: SM | D8: Abado | E8: 30 | F8: 21724.14 | G8: =+F8/30*E8 -> 21724.14 | H8: 4000 | I8: =1846.15*0 -> 0 | J8: =G8+H8+I8 -> 25724.14 | K8: =G8+H8+I8 -> 25724.14 | L8: =IF(K8<=2000,(0),IF(K8<=4000,(K8*0.15)-300,IF(K8<=7000,(K8*0.2)-500,IF(K8<=10000,(K8*0.25)-850,IF(K8<=14000,(K8*0.3)-1350,IF(K8>14000,(K8*0.35)-2050)))))) -> 6953.449 | M8: =F8*0.07 -> 1520.6898 | N8: =F8*0.11 -> 2389.6554 | P8: =L8+M8+O8 -> 8474.1388 | Q8: 2000 | R8: =J8-P8+Q8 -> 19250.001
A9: 4 | B9: Abezash Yeneneh | C9: Cleaner | D9: Wessen | E9: 30 | F9: 2179.49 | G9: =+F9/30*E9 -> 2179.49 | J9: =G9+H9+I9 -> 2179.49 | K9: =G9+H9+I9 -> 2179.49 | L9: =IF(K9<=2000,(0),IF(K9<=4000,(K9*0.15)-300,IF(K9<=7000,(K9*0.2)-500,IF(K9<=10000,(K9*0.25)-850,IF(K9<=14000,(K9*0.3)-1350,IF(K9>14000,(K9*0.35)-2050)))))) -> 26.9235 | M9: =F9*0.07 -> 152.5643 | N9: =F9*0.11 -> 239.7439 | P9: =L9+M9+O9 -> 179.4878 | Q9: 500 | R9: =J9-P9+Q9 -> 2500.0022
A10: 5 | B10: Abdurehman Assefa | C10: BA coordinator | D10: 4KILO | E10: 30 | F10: 4794.52 | G10: =+F10/30*E10 -> 4794.52 | I10: =2654.34*0.5 -> 1327.17 | J10: =G10+H10+I10 -> 6121.69 | K10: =G10+H10+I10 -> 6121.69 | L10: =IF(K10<=2000,(0),IF(K10<=4000,(K10*0.15)-300,IF(K10<=7000,(K10*0.2)-500,IF(K10<=10000,(K10*0.25)-850,IF(K10<=14000,(K10*0.3)-1350,IF(K10>14000,(K10*0.35)-2050)))))) -> 724.338 | M10: =F10*0.07 -> 335.6164 | N10: =F10*0.11 -> 527.3972 | P10: =L10+M10+O10 -> 1059.9544 | Q10: =1000/30*E10 -> 1000 | R10: =J10-P10+Q10 -> 6061.7356
A11: 6 | B11: Adelal Muhabaw | C11: BA coordinator | D11: Kara | E11: 30 | F11: 4794.52 | G11: =+F11/30*E11 -> 4794.52 | I11: =2654.34*0.5 -> 1327.17 | J11: =G11+H11+I11 -> 6121.69 | K11: =G11+H11+I11 -> 6121.69 | L11: =IF(K11<=2000,(0),IF(K11<=4000,(K11*0.15)-300,IF(K11<=7000,(K11*0.2)-500,IF(K11<=10000,(K11*0.25)-850,IF(K11<=14000,(K11*0.3)-1350,IF(K11>14000,(K11*0.35)-2050)))))) -> 724.338 | P11: =L11+M11+O11 -> 724.338 | Q11: =1000/30*E11 -> 1000 | R11: =J11-P11+Q11 -> 6397.352
A12: 7 | B12: Alemi Yadafa | C12: Cleaner | D12: BoleArabsa | E12: 30 | F12: 1612.9 | G12: =+F12/30*E12 -> 1612.9 | J12: =G12+H12+I12 -> 1612.9 | K12: =G12+H12+I12 -> 1612.9 | L12: =IF(K12<=2000,(0),IF(K12<=4000,(K12*0.15)-300,IF(K12<=7000,(K12*0.2)-500,IF(K12<=10000,(K12*0.25)-850,IF(K12<=14000,(K12*0.3)-1350,IF(K12>14000,(K12*0.35)-2050)))))) -> 0 | M12: =F12*0.07 -> 112.903 | N12: =F12*0.11 -> 177.419 | P12: =L12+M12+O12 -> 112.903 | R12: =J12-P12+Q12 -> 1499.997
A13: 8 | B13: Alem Seifu | C13: Cleaner | D13: 6KILO | E13: 30 | F13: 1612.9 | G13: =+F13/30*E13 -> 1612.9 | J13: =G13+H13+I13 -> 1612.9 | K13: =G13+H13+I13 -> 1612.9 | L13: =IF(K13<=2000,(0),IF(K13<=4000,(K13*0.15)-300,IF(K13<=7000,(K13*0.2)-500,IF(K13<=10000,(K13*0.25)-850,IF(K13<=14000,(K13*0.3)-1350,IF(K13>14000,(K13*0.35)-2050)))))) -> 0 | M13: =F13*0.07 -> 112.903 | N13: =F13*0.11 -> 177.419 | P13: =L13+M13+O13 -> 112.903 | R13: =J13-P13+Q13 -> 1499.997
A14: 9 | B14: Alemnesh Asfaw | C14: DSP | D14: Kara | E14: 30 | F14: 8007.94 | G14: =+F14/30*E14 -> 8007.94 | I14: =2857.14*1 -> 2857.14 | J14: =G14+H14+I14 -> 10865.08 | K14: =G14+H14+I14 -> 10865.08 | L14: =IF(K14<=2000,(0),IF(K14<=4000,(K14*0.15)-300,IF(K14<=7000,(K14*0.2)-500,IF(K14<=10000,(K14*0.25)-850,IF(K14<=14000,(K14*0.3)-1350,IF(K14>14000,(K14*0.35)-2050)))))) -> 1909.524 | M14: =F14*0.07 -> 560.5558 | N14: =F14*0.11 -> 880.8734 | P14: =L14+M14+O14 -> 2470.0798 | Q14: 1000 | R14: =J14-P14+Q14 -> 9395.0002
A15: 10 | B15: Alemtsehay Ashine | C15: HR MANAGER | D15: Head Office | E15: 30 | F15: 82672.41 | G15: =+F15/30*E15 -> 82672.41 | J15: =G15+H15+I15 -> 82672.41 | K15: =G15+H15+I15 -> 82672.41 | L15: =IF(K15<=2000,(0),IF(K15<=4000,(K15*0.15)-300,IF(K15<=7000,(K15*0.2)-500,IF(K15<=10000,(K15*0.25)-850,IF(K15<=14000,(K15*0.3)-1350,IF(K15>14000,(K15*0.35)-2050)))))) -> 26885.343 | M15: =F15*0.07 -> 5787.0687 | N15: =F15*0.11 -> 9093.9651 | P15: =L15+M15+O15 -> 32672.412 | Q15: =2000 -> 2000 | R15: =J15-P15+Q15 -> 51999.998
A16: 11 | B16: Amanuel Abebe | C16: HR OFFICER | D16: Head Office | E16: 30 | F16: 26594.82 | G16: =+F16/30*E16 -> 26594.82 | J16: =G16+H16+I16 -> 26594.82 | K16: =G16+H16+I16 -> 26594.82 | L16: =IF(K16<=2000,(0),IF(K16<=4000,(K16*0.15)-300,IF(K16<=7000,(K16*0.2)-500,IF(K16<=10000,(K16*0.25)-850,IF(K16<=14000,(K16*0.3)-1350,IF(K16>14000,(K16*0.35)-2050)))))) -> 7258.187 | M16: =F16*0.07 -> 1861.6374 | N16: =F16*0.11 -> 2925.4302 | P16: =L16+M16+O16 -> 9119.8244 | Q16: 1000 | R16: =J16-P16+Q16 -> 18474.996
A17: 12 | B17: Andualem Assefa | C17: Finance Director | D17: Head Office | E17: 30 | F17: 110258.62 | G17: =+F17/30*E17 -> 110258.62 | I17: 23076.92 | J17: =G17+H17+I17 -> 133335.54 | K17: =G17+H17+I17 -> 133335.54 | L17: =IF(K17<=2000,(0),IF(K17<=4000,(K17*0.15)-300,IF(K17<=7000,(K17*0.2)-500,IF(K17<=10000,(K17*0.25)-850,IF(K17<=14000,(K17*0.3)-1350,IF(K17>14000,(K17*0.35)-2050)))))) -> 44617.439 | M17: =F17*0.07 -> 7718.1034 | N17: =F17*0.11 -> 12128.448 | P17: =L17+M17+O17 -> 52335.542 | Q17: 4000 | R17: =J17-P17+Q17 -> 84999.998
A18: 13 | B18: Andualem Getachew | C18: IT | D18: Head Office | E18: 30 | F18: 48189.66 | G18: =+F18/30*E18 -> 48189.66 | J18: =G18+H18+I18 -> 48189.66 | K18: =G18+H18+I18 -> 48189.66 | L18: =IF(K18<=2000,(0),IF(K18<=4000,(K18*0.15)-300,IF(K18<=7000,(K18*0.2)-500,IF(K18<=10000,(K18*0.25)-850,IF(K18<=14000,(K18*0.3)-1350,IF(K18>14000,(K18*0.35)-2050)))))) -> 14816.381 | M18: =F18*0.07 -> 3373.2762 | P18: =L18+M18+O18 -> 18189.657 | Q18: =2000+1000 -> 3000 | R18: =J18-P18+Q18 -> 33000.003
A19: 14 | B19: Asiya Abera | C19: SM | D19: Shiromeda | E19: 30 | F19: 21724.14 | G19: =+F19/30*E19 -> 21724.14 | I19: =1846.15*0 -> 0 | J19: =G19+H19+I19 -> 21724.14 | K19: =G19+H19+I19 -> 21724.14 | L19: =IF(K19<=2000,(0),IF(K19<=4000,(K19*0.15)-300,IF(K19<=7000,(K19*0.2)-500,IF(K19<=10000,(K19*0.25)-850,IF(K19<=14000,(K19*0.3)-1350,IF(K19>14000,(K19*0.35)-2050)))))) -> 5553.449 | M19: =F19*0.07 -> 1520.6898 | N19: =F19*0.11 -> 2389.6554 | P19: =L19+M19+O19 -> 7074.1388 | Q19: =2000 -> 2000 | R19: =J19-P19+Q19 -> 16650.001
A20: 15 | B20: Atalel Talasebaw | C20: Cleaner | D20: AYAT49 | E20: 30 | F20: 1612.9 | G20: =+F20/30*E20 -> 1612.9 | J20: =G20+H20+I20 -> 1612.9 | K20: =G20+H20+I20 -> 1612.9 | L20: =IF(K20<=2000,(0),IF(K20<=4000,(K20*0.15)-300,IF(K20<=7000,(K20*0.2)-500,IF(K20<=10000,(K20*0.25)-850,IF(K20<=14000,(K20*0.3)-1350,IF(K20>14000,(K20*0.35)-2050)))))) -> 0 | M20: =F20*0.07 -> 112.903 | N20: =F20*0.11 -> 177.419 | P20: =L20+M20+O20 -> 112.903 | R20: =J20-P20+Q20 -> 1499.997
A21: 16 | B21: Aynalem Bayssa Feyssa | C21: Accountant | D21: Head Office | E21: 30 | F21: 17155.17 | G21: =+F21/30*E21 -> 17155.17 | J21: =G21+H21+I21 -> 17155.17 | K21: =G21+H21+I21 -> 17155.17 | L21: =IF(K21<=2000,(0),IF(K21<=4000,(K21*0.15)-300,IF(K21<=7000,(K21*0.2)-500,IF(K21<=10000,(K21*0.25)-850,IF(K21<=14000,(K21*0.3)-1350,IF(K21>14000,(K21*0.35)-2050)))))) -> 3954.3095 | M21: =F21*0.07 -> 1200.8619 | N21: =F21*0.11 -> 1887.0687 | P21: =L21+M21+O21 -> 5155.1714 | Q21: 1500 | R21: =J21-P21+Q21 -> 13499.999
A22: 17 | B22: Betelhem Million | C22: DSP | D22: Megenagna | E22: 30 | F22: 8007.94 | G22: =+F22/30*E22 -> 8007.94 | I22: =2857.14/30*E22 -> 2857.14 | J22: =G22+H22+I22 -> 10865.08 | K22: =G22+H22+I22 -> 10865.08 | L22: =IF(K22<=2000,(0),IF(K22<=4000,(K22*0.15)-300,IF(K22<=7000,(K22*0.2)-500,IF(K22<=10000,(K22*0.25)-850,IF(K22<=14000,(K22*0.3)-1350,IF(K22>14000,(K22*0.35)-2050)))))) -> 1909.524 | M22: =F22*0.07 -> 560.5558 | N22: =F22*0.11 -> 880.8734 | P22: =L22+M22+O22 -> 2470.0798 | Q22: =1000 -> 1000 | R22: =J22-P22+Q22 -> 9395.0002
A23: 18 | B23: Betelhem Tesfaye | C23: S.Accountant | D23: AyatTafo | E23: 30 | F23: 11108.37 | G23: =+F23/30*E23 -> 11108.37 | I23: =2857.14 -> 2857.14 | J23: =G23+H23+I23 -> 13965.51 | K23: =G23+H23+I23 -> 13965.51 | L23: =IF(K23<=2000,(0),IF(K23<=4000,(K23*0.15)-300,IF(K23<=7000,(K23*0.2)-500,IF(K23<=10000,(K23*0.25)-850,IF(K23<=14000,(K23*0.3)-1350,IF(K23>14000,(K23*0.35)-2050)))))) -> 2839.653 | M23: =F23*0.07 -> 777.5859 | N23: =F23*0.11 -> 1221.9207 | P23: =L23+M23+O23 -> 3617.2389 | Q23: =1000+1200+740 -> 2940 | R23: =J23-P23+Q23 -> 13288.271
A24: 19 | B24: Belge Mola | C24: BA coordinator | D24: H/mariam | E24: 30 | F24: 4794.52 | G24: =+F24/30*E24 -> 4794.52 | I24: =2654.34/30*E24 -> 2654.34 | J24: =G24+H24+I24 -> 7448.86 | K24: =G24+H24+I24 -> 7448.86 | L24: =IF(K24<=2000,(0),IF(K24<=4000,(K24*0.15)-300,IF(K24<=7000,(K24*0.2)-500,IF(K24<=10000,(K24*0.25)-850,IF(K24<=14000,(K24*0.3)-1350,IF(K24>14000,(K24*0.35)-2050)))))) -> 1012.215 | M24: =F24*0.07 -> 335.6164 | N24: =F24*0.11 -> 527.3972 | P24: =L24+M24+O24 -> 1347.8314 | Q24: =1000/30*E24 -> 1000 | R24: =J24-P24+Q24 -> 7101.0286
A25: 20 | B25: Bogal Bekele | C25: Security | D25: Fiyelbet | E25: 30 | F25: 5084.07 | G25: =+F25/30*E25 -> 5084.07 | H25: =Overtime!I5 -> 2933.1173 | J25: =G25+H25+I25 -> 8017.1873 | K25: =G25+H25+I25 -> 8017.1873 | L25: =IF(K25<=2000,(0),IF(K25<=4000,(K25*0.15)-300,IF(K25<=7000,(K25*0.2)-500,IF(K25<=10000,(K25*0.25)-850,IF(K25<=14000,(K25*0.3)-1350,IF(K25>14000,(K25*0.35)-2050)))))) -> 1154.2968 | M25: =F25*0.07 -> 355.8849 | N25: =F25*0.11 -> 559.2477 | O25: 2500 | P25: =L25+M25+O25 -> 4010.1817 | R25: =J25-P25+Q25 -> 4007.0056
A26: 21 | B26: Dagim Mengistu | C26: Driver | D26: Head Office | E26: 30 | F26: 14655.17 | G26: =+F26/30*E26 -> 14655.17 | I26: 3076.93 | J26: =G26+H26+I26 -> 17732.1 | K26: =G26+H26+I26 -> 17732.1 | L26: =IF(K26<=2000,(0),IF(K26<=4000,(K26*0.15)-300,IF(K26<=7000,(K26*0.2)-500,IF(K26<=10000,(K26*0.25)-850,IF(K26<=14000,(K26*0.3)-1350,IF(K26>14000,(K26*0.35)-2050)))))) -> 4156.235 | M26: =F26*0.07 -> 1025.8619 | N26: =F26*0.11 -> 1612.0687 | O26: 4000 | P26: =L26+M26+O26 -> 9182.0969 | Q26: =1000/30*E26 -> 1000 | R26: =J26-P26+Q26 -> 9550.0031
A27: 22 | B27: Dinar Kahisay Berhe | C27: SM | D27: Wessen | E27: 30 | F27: 20603.45 | G27: =+F27/30*E27 -> 20603.45 | I27: =1846.15*0 -> 0 | J27: =G27+H27+I27 -> 20603.45 | K27: =G27+H27+I27 -> 20603.45 | L27: =IF(K27<=2000,(0),IF(K27<=4000,(K27*0.15)-300,IF(K27<=7000,(K27*0.2)-500,IF(K27<=10000,(K27*0.25)-850,IF(K27<=14000,(K27*0.3)-1350,IF(K27>14000,(K27*0.35)-2050)))))) -> 5161.2075 | M27: =F27*0.07 -> 1442.2415 | N27: =F27*0.11 -> 2266.3795 | P27: =L27+M27+O27 -> 6603.449 | Q27: =2000/30*E27 -> 2000 | R27: =J27-P27+Q27 -> 16000.001
A28: 23 | B28: Eden Ambaw | C28: DSP | D28: Fiyelbet | E28: 30 | F28: 7573.53 | G28: =+F28/30*E28 -> 7573.53 | I28: =2857.14/30*E28 -> 2857.14 | J28: =G28+H28+I28 -> 10430.67 | K28: =G28+H28+I28 -> 10430.67 | L28: =IF(K28<=2000,(0),IF(K28<=4000,(K28*0.15)-300,IF(K28<=7000,(K28*0.2)-500,IF(K28<=10000,(K28*0.25)-850,IF(K28<=14000,(K28*0.3)-1350,IF(K28>14000,(K28*0.35)-2050)))))) -> 1779.201 | M28: =F28*0.07 -> 530.1471 | N28: =F28*0.11 -> 833.0883 | P28: =L28+M28+O28 -> 2309.3481 | Q28: =1000/30*E28 -> 1000 | R28: =J28-P28+Q28 -> 9121.3219
A29: 24 | B29: Emebet Belete | C29: Cleaner | D29: Summit | E29: 30 | F29: 2381.41 | G29: =+F29/30*E29 -> 2381.41 | J29: =G29+H29+I29 -> 2381.41 | K29: =G29+H29+I29 -> 2381.41 | L29: =IF(K29<=2000,(0),IF(K29<=4000,(K29*0.15)-300,IF(K29<=7000,(K29*0.2)-500,IF(K29<=10000,(K29*0.25)-850,IF(K29<=14000,(K29*0.3)-1350,IF(K29>14000,(K29*0.35)-2050)))))) -> 57.2115 | M29: =F29*0.07 -> 166.6987 | N29: =F29*0.11 -> 261.9551 | P29: =L29+M29+O29 -> 223.9102 | R29: =J29-P29+Q29 -> 2157.4998
A30: 25 | B30: Enat Fiseha | C30: Cleaner | D30: Kara | E30: 30 | F30: 1044.44 | G30: =+F30/30*E30 -> 1044.44 | J30: =G30+H30+I30 -> 1044.44 | K30: =G30+H30+I30 -> 1044.44 | L30: =IF(K30<=2000,(0),IF(K30<=4000,(K30*0.15)-300,IF(K30<=7000,(K30*0.2)-500,IF(K30<=10000,(K30*0.25)-850,IF(K30<=14000,(K30*0.3)-1350,IF(K30>14000,(K30*0.35)-2050)))))) -> 0 | M30: =F30*0.07 -> 73.1108 | N30: =F30*0.11 -> 114.8884 | P30: =L30+M30+O30 -> 73.1108 | R30: =J30-P30+Q30 -> 971.3292
A31: 26 | B31: Enatenesh Tezera | C31: Cleaner | D31: Kara | E31: 30 | F31: 1600 | G31: =+F31/30*E31 -> 1600 | J31: =G31+H31+I31 -> 1600 | K31: =G31+H31+I31 -> 1600 | L31: =IF(K31<=2000,(0),IF(K31<=4000,(K31*0.15)-300,IF(K31<=7000,(K31*0.2)-500,IF(K31<=10000,(K31*0.25)-850,IF(K31<=14000,(K31*0.3)-1350,IF(K31>14000,(K31*0.35)-2050)))))) -> 0 | M31: =F31*0.07 -> 112 | N31: =F31*0.11 -> 176 | P31: =L31+M31+O31 -> 112 | R31: =J31-P31+Q31 -> 1488
A32: 27 | B32: Ekram Hussen Argaw | C32: DSP | D32: H/mariam | E32: 30 | F32: 7573.53 | G32: =+F32/30*E32 -> 7573.53 | I32: =2857.14/30*E32 -> 2857.14 | J32: =G32+H32+I32 -> 10430.67 | K32: =G32+H32+I32 -> 10430.67 | L32: =IF(K32<=2000,(0),IF(K32<=4000,(K32*0.15)-300,IF(K32<=7000,(K32*0.2)-500,IF(K32<=10000,(K32*0.25)-850,IF(K32<=14000,(K32*0.3)-1350,IF(K32>14000,(K32*0.35)-2050)))))) -> 1779.201 | M32: =F32*0.07 -> 530.1471 | N32: =F32*0.11 -> 833.0883 | P32: =L32+M32+O32 -> 2309.3481 | Q32: =1000/30*E32 -> 1000 | R32: =J32-P32+Q32 -> 9121.3219
A33: 28 | B33: Eyob Girma Ketema | C33: BA coordinator/Ebu Sales | D33: Megenagna | E33: 30 | F33: 13730.16 | G33: =+F33/30*E33 -> 13730.16 | I33: 1517.71 | J33: =G33+H33+I33 -> 15247.87 | K33: =G33+H33+I33 -> 15247.87 | L33: =IF(K33<=2000,(0),IF(K33<=4000,(K33*0.15)-300,IF(K33<=7000,(K33*0.2)-500,IF(K33<=10000,(K33*0.25)-850,IF(K33<=14000,(K33*0.3)-1350,IF(K33>14000,(K33*0.35)-2050)))))) -> 3286.7545 | P33: =L33+M33+O33 -> 3286.7545 | Q33: 1000 | R33: =J33-P33+Q33 -> 12961.115
A34: 29 | B34: Fantu Hailemariam | C34: Cleaner | D34: Megenagna | E34: 30 | F34: 1832.35 | G34: =+F34/30*E34 -> 1832.35 | J34: =G34+H34+I34 -> 1832.35 | K34: =G34+H34+I34 -> 1832.35 | L34: =IF(K34<=2000,(0),IF(K34<=4000,(K34*0.15)-300,IF(K34<=7000,(K34*0.2)-500,IF(K34<=10000,(K34*0.25)-850,IF(K34<=14000,(K34*0.3)-1350,IF(K34>14000,(K34*0.35)-2050)))))) -> 0 | P34: =L34+M34+O34 -> 0 | R34: =J34-P34+Q34 -> 1832.35
A35: 30 | B35: Fasika Girma | C35: S.Accountant | D35: Kechene | E35: 30 | F35: 9044.12 | G35: =+F35/30*E35 -> 9044.12 | I35: =2788.86/30*E35 -> 2788.86 | J35: =G35+H35+I35 -> 11832.98 | K35: =G35+H35+I35 -> 11832.98 | L35: =IF(K35<=2000,(0),IF(K35<=4000,(K35*0.15)-300,IF(K35<=7000,(K35*0.2)-500,IF(K35<=10000,(K35*0.25)-850,IF(K35<=14000,(K35*0.3)-1350,IF(K35>14000,(K35*0.35)-2050)))))) -> 2199.894 | M35: =F35*0.07 -> 633.0884 | N35: =F35*0.11 -> 994.8532 | P35: =L35+M35+O35 -> 2832.9824 | Q35: 1000 | R35: =J35-P35+Q35 -> 9999.9976
A36: 31 | B36: Feruza Jemal | C36: S.Accountant | D36: 4KILO | E36: 30 | F36: 9044.12 | G36: =+F36/30*E36 -> 9044.12 | I36: =2788.86 -> 2788.86 | J36: =G36+H36+I36 -> 11832.98 | K36: =G36+H36+I36 -> 11832.98 | L36: =IF(K36<=2000,(0),IF(K36<=4000,(K36*0.15)-300,IF(K36<=7000,(K36*0.2)-500,IF(K36<=10000,(K36*0.25)-850,IF(K36<=14000,(K36*0.3)-1350,IF(K36>14000,(K36*0.35)-2050)))))) -> 2199.894 | M36: =F36*0.07 -> 633.0884 | N36: =F36*0.11 -> 994.8532 | P36: =L36+M36+O36 -> 2832.9824 | Q36: 1000 | R36: =J36-P36+Q36 -> 9999.9976
A37: 32 | B37: Frewoini Haile | C37: S.Accountant | D37: Shiromeda | E37: 30 | F37: 11108.37 | G37: =+F37/30*E37 -> 11108.37 | I37: =2857.14*1 -> 2857.14 | J37: =G37+H37+I37 -> 13965.51 | K37: =G37+H37+I37 -> 13965.51 | L37: =IF(K37<=2000,(0),IF(K37<=4000,(K37*0.15)-300,IF(K37<=7000,(K37*0.2)-500,IF(K37<=10000,(K37*0.25)-850,IF(K37<=14000,(K37*0.3)-1350,IF(K37>14000,(K37*0.35)-2050)))))) -> 2839.653 | M37: =F37*0.07 -> 777.5859 | N37: =F37*0.11 -> 1221.9207 | P37: =L37+M37+O37 -> 3617.2389 | Q37: =1000+1200 -> 2200 | R37: =J37-P37+Q37 -> 12548.271
A38: 33 | B38: Genet Girma | C38: Cleaner | D38: AyatTafo | E38: 30 | F38: 1612.9 | G38: =+F38/30*E38 -> 1612.9 | J38: =G38+H38+I38 -> 1612.9 | K38: =G38+H38+I38 -> 1612.9 | L38: =IF(K38<=2000,(0),IF(K38<=4000,(K38*0.15)-300,IF(K38<=7000,(K38*0.2)-500,IF(K38<=10000,(K38*0.25)-850,IF(K38<=14000,(K38*0.3)-1350,IF(K38>14000,(K38*0.35)-2050)))))) -> 0 | M38: =F38*0.07 -> 112.903 | N38: =F38*0.11 -> 177.419 | P38: =L38+M38+O38 -> 112.903 | R38: =J38-P38+Q38 -> 1499.997
A39: 34 | B39: Genet G/tsadik | C39: Cleaner | D39: Head Office | E39: 30 | F39: 5913.34 | G39: =+F39/30*E39 -> 5913.34 | J39: =G39+H39+I39 -> 5913.34 | K39: =G39+H39+I39 -> 5913.34 | L39: =IF(K39<=2000,(0),IF(K39<=4000,(K39*0.15)-300,IF(K39<=7000,(K39*0.2)-500,IF(K39<=10000,(K39*0.25)-850,IF(K39<=14000,(K39*0.3)-1350,IF(K39>14000,(K39*0.35)-2050)))))) -> 682.668 | P39: =L39+M39+O39 -> 682.668 | Q39: 2000 | R39: =J39-P39+Q39 -> 7230.672
A40: 35 | B40: Genet Legese Kuma | C40: Accountant | D40: Head Office | E40: 30 | F40: 18879.31 | G40: =+F40/30*E40 -> 18879.31 | J40: =G40+H40+I40 -> 18879.31 | K40: =G40+H40+I40 -> 18879.31 | L40: =IF(K40<=2000,(0),IF(K40<=4000,(K40*0.15)-300,IF(K40<=7000,(K40*0.2)-500,IF(K40<=10000,(K40*0.25)-850,IF(K40<=14000,(K40*0.3)-1350,IF(K40>14000,(K40*0.35)-2050)))))) -> 4557.7585 | M40: =F40*0.07 -> 1321.5517 | N40: =F40*0.11 -> 2076.7241 | P40: =L40+M40+O40 -> 5879.3102 | Q40: 1500 | R40: =J40-P40+Q40 -> 14500
A41: 36 | B41: Genzeb Degif | C41: BA coordinator | D41: Summit | E41: 30 | F41: 4794.52 | G41: =+F41/30*E41 -> 4794.52 | I41: =2654.34/30*E41 -> 2654.34 | J41: =G41+H41+I41 -> 7448.86 | K41: =G41+H41+I41 -> 7448.86 | L41: =IF(K41<=2000,(0),IF(K41<=4000,(K41*0.15)-300,IF(K41<=7000,(K41*0.2)-500,IF(K41<=10000,(K41*0.25)-850,IF(K41<=14000,(K41*0.3)-1350,IF(K41>14000,(K41*0.35)-2050)))))) -> 1012.215 | M41: =F41*0.07 -> 335.6164 | N41: =F41*0.11 -> 527.3972 | P41: =L41+M41+O41 -> 1347.8314 | Q41: =1000/30*E41 -> 1000 | R41: =J41-P41+Q41 -> 7101.0286
A42: 37 | B42: Guluma chekolu | C42: DSP | D42: BoleArabsa | E42: 30 | F42: 7124.27 | G42: =+F42/30*E42 -> 7124.27 | I42: 3480.15 | J42: =G42+H42+I42 -> 10604.42 | K42: =G42+H42+I42 -> 10604.42 | L42: =IF(K42<=2000,(0),IF(K42<=4000,(K42*0.15)-300,IF(K42<=7000,(K42*0.2)-500,IF(K42<=10000,(K42*0.25)-850,IF(K42<=14000,(K42*0.3)-1350,IF(K42>14000,(K42*0.35)-2050)))))) -> 1831.326 | M42: =F42*0.07 -> 498.6989 | N42: =F42*0.11 -> 783.6697 | P42: =L42+M42+O42 -> 2330.0249 | Q42: =1000 -> 1000 | R42: =J42-P42+Q42 -> 9274.3951
A43: 38 | B43: Habtamu Nega Ejigu | C43: BA coordinator | D43: BoleArabsa | E43: 30 | F43: 4794.52 | G43: =+F43/30*E43 -> 4794.52 | J43: =G43+H43+I43 -> 4794.52 | K43: =G43+H43+I43 -> 4794.52 | L43: =IF(K43<=2000,(0),IF(K43<=4000,(K43*0.15)-300,IF(K43<=7000,(K43*0.2)-500,IF(K43<=10000,(K43*0.25)-850,IF(K43<=14000,(K43*0.3)-1350,IF(K43>14000,(K43*0.35)-2050)))))) -> 458.904 | P43: =L43+M43+O43 -> 458.904 | Q43: =1000/30*E43 -> 1000 | R43: =J43-P43+Q43 -> 5335.616
A44: 39 | B44: Halefom Shiferaw | C44: SM | D44: Fiyelbet | E44: 30 | F44: 20603.45 | G44: =+F44/30*E44 -> 20603.45 | I44: =1846.15*0 -> 0 | J44: =G44+H44+I44 -> 20603.45 | K44: =G44+H44+I44 -> 20603.45 | L44: =IF(K44<=2000,(0),IF(K44<=4000,(K44*0.15)-300,IF(K44<=7000,(K44*0.2)-500,IF(K44<=10000,(K44*0.25)-850,IF(K44<=14000,(K44*0.3)-1350,IF(K44>14000,(K44*0.35)-2050)))))) -> 5161.2075 | M44: =F44*0.07 -> 1442.2415 | N44: =F44*0.11 -> 2266.3795 | P44: =L44+M44+O44 -> 6603.449 | Q44: 2000 | R44: =J44-P44+Q44 -> 16000.001
A45: 40 | B45: Hawi Jifera | C45: DSP | D45: Wessen | E45: 16 | F45: 7573.53 | G45: =+F45/30*E45 -> 4039.216 | I45: =2683.83/30*E45 -> 1431.376 | J45: =G45+H45+I45 -> 5470.592 | K45: =G45+H45+I45 -> 5470.592 | L45: =IF(K45<=2000,(0),IF(K45<=4000,(K45*0.15)-300,IF(K45<=7000,(K45*0.2)-500,IF(K45<=10000,(K45*0.25)-850,IF(K45<=14000,(K45*0.3)-1350,IF(K45>14000,(K45*0.35)-2050)))))) -> 594.1184 | M45: =F45*0.07 -> 530.1471 | N45: =F45*0.11 -> 833.0883 | P45: =L45+M45+O45 -> 1124.2655 | Q45: 2000 | R45: =J45-P45+Q45 -> 6346.3265
A46: 41 | B46: Helen G/Tinsae | C46: Shop SV | D46: Summit | E46: 30 | F46: 17155.18 | G46: =+F46/30*E46 -> 17155.18 | H46: 5000 | I46: =1846.15*0 -> 0 | J46: =G46+H46+I46 -> 22155.18 | K46: =G46+H46+I46 -> 22155.18 | L46: =IF(K46<=2000,(0),IF(K46<=4000,(K46*0.15)-300,IF(K46<=7000,(K46*0.2)-500,IF(K46<=10000,(K46*0.25)-850,IF(K46<=14000,(K46*0.3)-1350,IF(K46>14000,(K46*0.35)-2050)))))) -> 5704.313 | M46: =F46*0.07 -> 1200.8626 | N46: =F46*0.11 -> 1887.0698 | P46: =L46+M46+O46 -> 6905.1756 | Q46: 1000 | R46: =J46-P46+Q46 -> 16250.004
A47: 42 | B47: Helina Deribew | C47: Shop SV | D47: BoleArabsa | E47: 30 | F47: 17155.18 | G47: =+F47/30*E47 -> 17155.18 | I47: =1846.15*0 -> 0 | J47: =G47+H47+I47 -> 17155.18 | K47: =G47+H47+I47 -> 17155.18 | L47: =IF(K47<=2000,(0),IF(K47<=4000,(K47*0.15)-300,IF(K47<=7000,(K47*0.2)-500,IF(K47<=10000,(K47*0.25)-850,IF(K47<=14000,(K47*0.3)-1350,IF(K47>14000,(K47*0.35)-2050)))))) -> 3954.313 | M47: =F47*0.07 -> 1200.8626 | N47: =F47*0.11 -> 1887.0698 | P47: =L47+M47+O47 -> 5155.1756 | Q47: 1000 | R47: =J47-P47+Q47 -> 13000.004
A48: 43 | B48: Heran Aboye | C48: S.Accountant | D48: Wessen | E48: 30 | F48: 9044.12 | G48: =+F48/30*E48 -> 9044.12 | I48: =2788.86/30*E48 -> 2788.86 | J48: =G48+H48+I48 -> 11832.98 | K48: =G48+H48+I48 -> 11832.98 | L48: =IF(K48<=2000,(0),IF(K48<=4000,(K48*0.15)-300,IF(K48<=7000,(K48*0.2)-500,IF(K48<=10000,(K48*0.25)-850,IF(K48<=14000,(K48*0.3)-1350,IF(K48>14000,(K48*0.35)-2050)))))) -> 2199.894 | M48: =F48*0.07 -> 633.0884 | N48: =F48*0.11 -> 994.8532 | P48: =L48+M48+O48 -> 2832.9824 | Q48: =1000/30*E48 -> 1000 | R48: =J48-P48+Q48 -> 9999.9976
A49: 44 | B49: Hermela Arega | C49: S.Accountant | D49: Ayat49 | E49: 30 | F49: 9044.12 | G49: =+F49/30*E49 -> 9044.12 | I49: =2788.86 -> 2788.86 | J49: =G49+H49+I49 -> 11832.98 | K49: =G49+H49+I49 -> 11832.98 | L49: =IF(K49<=2000,(0),IF(K49<=4000,(K49*0.15)-300,IF(K49<=7000,(K49*0.2)-500,IF(K49<=10000,(K49*0.25)-850,IF(K49<=14000,(K49*0.3)-1350,IF(K49>14000,(K49*0.35)-2050)))))) -> 2199.894 | M49: =F49*0.07 -> 633.0884 | N49: =F49*0.11 -> 994.8532 | P49: =L49+M49+O49 -> 2832.9824 | Q49: 1000 | R49: =J49-P49+Q49 -> 9999.9976
A50: 45 | B50: Hermon Firew | C50: Shop SV | D50: Kechene | E50: 30 | F50: 18103.45 | G50: =+F50/30*E50 -> 18103.45 | H50: 2000 | I50: =1846.15*0 -> 0 | J50: =G50+H50+I50 -> 20103.45 | K50: =G50+H50+I50 -> 20103.45 | L50: =IF(K50<=2000,(0),IF(K50<=4000,(K50*0.15)-300,IF(K50<=7000,(K50*0.2)-500,IF(K50<=10000,(K50*0.25)-850,IF(K50<=14000,(K50*0.3)-1350,IF(K50>14000,(K50*0.35)-2050)))))) -> 4986.2075 | M50: =F50*0.07 -> 1267.2415 | N50: =F50*0.11 -> 1991.3795 | P50: =L50+M50+O50 -> 6253.449 | Q50: 1000 | R50: =J50-P50+Q50 -> 14850.001
A51: 46 | B51: Hirut Mamo | C51: DSP | D51: AYAT49 | E51: 30 | F51: 7573.53 | G51: =+F51/30*E51 -> 7573.53 | I51: =2683.83/30*E51 -> 2683.83 | J51: =G51+H51+I51 -> 10257.36 | K51: =G51+H51+I51 -> 10257.36 | L51: =IF(K51<=2000,(0),IF(K51<=4000,(K51*0.15)-300,IF(K51<=7000,(K51*0.2)-500,IF(K51<=10000,(K51*0.25)-850,IF(K51<=14000,(K51*0.3)-1350,IF(K51>14000,(K51*0.35)-2050)))))) -> 1727.208 | M51: =F51*0.07 -> 530.1471 | N51: =F51*0.11 -> 833.0883 | P51: =L51+M51+O51 -> 2257.3551 | Q51: =1000+740 -> 1740 | R51: =J51-P51+Q51 -> 9740.0049
A52: 47 | B52: Jilalu Kedir Shifa | C52: Accountant | D52: Head Office | E52: 30 | F52: 28448.28 | G52: =+F52/30*E52 -> 28448.28 | J52: =G52+H52+I52 -> 28448.28 | K52: =G52+H52+I52 -> 28448.28 | L52: =IF(K52<=2000,(0),IF(K52<=4000,(K52*0.15)-300,IF(K52<=7000,(K52*0.2)-500,IF(K52<=10000,(K52*0.25)-850,IF(K52<=14000,(K52*0.3)-1350,IF(K52>14000,(K52*0.35)-2050)))))) -> 7906.898 | M52: =F52*0.07 -> 1991.3796 | N52: =F52*0.11 -> 3129.3108 | P52: =L52+M52+O52 -> 9898.2776 | Q52: 1500 | R52: =J52-P52+Q52 -> 20050.002
A53: 48 | B53: Kibrom Kahisay | C53: Technician | D53: Head Office | E53: 9 | F53: 27500 | G53: =+F53/30*E53 -> 8250 | J53: =G53+H53+I53 -> 8250 | K53: =G53+H53+I53 -> 8250 | L53: =IF(K53<=2000,(0),IF(K53<=4000,(K53*0.15)-300,IF(K53<=7000,(K53*0.2)-500,IF(K53<=10000,(K53*0.25)-850,IF(K53<=14000,(K53*0.3)-1350,IF(K53>14000,(K53*0.35)-2050)))))) -> 1212.5 | P53: =L53+M53+O53 -> 1212.5 | Q53: =2000/30*E53 -> 600 | R53: =J53-P53+Q53 -> 7637.5
A54: 49 | B54: Kidist Alebachew | C54: Distribution MGR | D54: Head Office | E54: 30 | F54: 35344.83 | G54: =+F54/30*E54 -> 35344.83 | I54: =6153.85 -> 6153.85 | J54: =G54+H54+I54 -> 41498.68 | K54: =G54+H54+I54 -> 41498.68 | L54: =IF(K54<=2000,(0),IF(K54<=4000,(K54*0.15)-300,IF(K54<=7000,(K54*0.2)-500,IF(K54<=10000,(K54*0.25)-850,IF(K54<=14000,(K54*0.3)-1350,IF(K54>14000,(K54*0.35)-2050)))))) -> 12474.538 | M54: =F54*0.07 -> 2474.1381 | N54: =F54*0.11 -> 3887.9313 | P54: =L54+M54+O54 -> 14948.676 | Q54: 2000 | R54: =J54-P54+Q54 -> 28550.004
A55: 50 | B55: Kidist Asmar Bihonilign | C55: Shop SV | D55: 4KILO | E55: 7 | F55: 18879.31 | G55: =+F55/30*E55 -> 4405.1723 | I55: =1538.46/30*E55 -> 358.974 | J55: =G55+H55+I55 -> 4764.1463 | K55: =G55+H55+I55 -> 4764.1463 | L55: =IF(K55<=2000,(0),IF(K55<=4000,(K55*0.15)-300,IF(K55<=7000,(K55*0.2)-500,IF(K55<=10000,(K55*0.25)-850,IF(K55<=14000,(K55*0.3)-1350,IF(K55>14000,(K55*0.35)-2050)))))) -> 452.82927 | P55: =L55+M55+O55 -> 452.82927 | Q55: =1000/30*E55 -> 233.33333 | R55: =J55-P55+Q55 -> 4544.6504
A56: 51 | B56: Kirsnesh Eshete | C56: S.Accountant | D56: Fiyelbet | E56: 30 | F56: 9044.12 | G56: =+F56/30*E56 -> 9044.12 | I56: 2788.86 | J56: =G56+H56+I56 -> 11832.98 | K56: =G56+H56+I56 -> 11832.98 | L56: =IF(K56<=2000,(0),IF(K56<=4000,(K56*0.15)-300,IF(K56<=7000,(K56*0.2)-500,IF(K56<=10000,(K56*0.25)-850,IF(K56<=14000,(K56*0.3)-1350,IF(K56>14000,(K56*0.35)-2050)))))) -> 2199.894 | M56: =F56*0.07 -> 633.0884 | N56: =F56*0.11 -> 994.8532 | P56: =L56+M56+O56 -> 2832.9824 | Q56: 1000 | R56: =J56-P56+Q56 -> 9999.9976
A57: 52 | B57: Kirubel Tegafaw | C57: DSP | D57: 6KILO | E57: 30 | F57: 8007.94 | G57: =+F57/30*E57 -> 8007.94 | I57: =2857.14 -> 2857.14 | J57: =G57+H57+I57 -> 10865.08 | K57: =G57+H57+I57 -> 10865.08 | L57: =IF(K57<=2000,(0),IF(K57<=4000,(K57*0.15)-300,IF(K57<=7000,(K57*0.2)-500,IF(K57<=10000,(K57*0.25)-850,IF(K57<=14000,(K57*0.3)-1350,IF(K57>14000,(K57*0.35)-2050)))))) -> 1909.524 | M57: =F57*0.07 -> 560.5558 | N57: =F57*0.11 -> 880.8734 | P57: =L57+M57+O57 -> 2470.0798 | Q57: 1000 | R57: =J57-P57+Q57 -> 9395.0002
A58: 53 | B58: Konjit Ashenafi | C58: BA coordinator | D58: Megenagna | E58: 30 | F58: 4794.52 | G58: =+F58/30*E58 -> 4794.52 | I58: =2654.34/30*E58 -> 2654.34 | J58: =G58+H58+I58 -> 7448.86 | K58: =G58+H58+I58 -> 7448.86 | L58: =IF(K58<=2000,(0),IF(K58<=4000,(K58*0.15)-300,IF(K58<=7000,(K58*0.2)-500,IF(K58<=10000,(K58*0.25)-850,IF(K58<=14000,(K58*0.3)-1350,IF(K58>14000,(K58*0.35)-2050)))))) -> 1012.215 | M58: =F58*0.07 -> 335.6164 | N58: =F58*0.11 -> 527.3972 | P58: =L58+M58+O58 -> 1347.8314 | Q58: =1000/30*E58 -> 1000 | R58: =J58-P58+Q58 -> 7101.0286
A59: 54 | B59: Leul Tilaye | C59: BA coordinator | D59: Abado | E59: 29 | F59: 4794.52 | G59: =+F59/30*E59 -> 4634.7027 | I59: =2519.64 -> 2519.64 | J59: =G59+H59+I59 -> 7154.3427 | K59: =G59+H59+I59 -> 7154.3427 | L59: =IF(K59<=2000,(0),IF(K59<=4000,(K59*0.15)-300,IF(K59<=7000,(K59*0.2)-500,IF(K59<=10000,(K59*0.25)-850,IF(K59<=14000,(K59*0.3)-1350,IF(K59>14000,(K59*0.35)-2050)))))) -> 938.58567 | M59: =F59*0.07 -> 335.6164 | N59: =F59*0.11 -> 527.3972 | P59: =L59+M59+O59 -> 1274.2021 | Q59: =1000 -> 1000 | R59: =J59-P59+Q59 -> 6880.1406
A60: 55 | B60: Made Geta | C60: DSP | D60: Kara | E60: 30 | F60: 7573.53 | G60: =+F60/30*E60 -> 7573.53 | I60: =2683.83/30*E60 -> 2683.83 | J60: =G60+H60+I60 -> 10257.36 | K60: =G60+H60+I60 -> 10257.36 | L60: =IF(K60<=2000,(0),IF(K60<=4000,(K60*0.15)-300,IF(K60<=7000,(K60*0.2)-500,IF(K60<=10000,(K60*0.25)-850,IF(K60<=14000,(K60*0.3)-1350,IF(K60>14000,(K60*0.35)-2050)))))) -> 1727.208 | M60: =F60*0.07 -> 530.1471 | N60: =F60*0.11 -> 833.0883 | P60: =L60+M60+O60 -> 2257.3551 | Q60: =1000/30*E60 -> 1000 | R60: =J60-P60+Q60 -> 9000.0049
A61: 56 | B61: Mahlet Solomon | C61: SM | D61: AYAT49 | E61: 30 | F61: 18103.45 | G61: =+F61/30*E61 -> 18103.45 | H61: 2000 | I61: =1846.15*0 -> 0 | J61: =G61+H61+I61 -> 20103.45 | K61: =G61+H61+I61 -> 20103.45 | L61: =IF(K61<=2000,(0),IF(K61<=4000,(K61*0.15)-300,IF(K61<=7000,(K61*0.2)-500,IF(K61<=10000,(K61*0.25)-850,IF(K61<=14000,(K61*0.3)-1350,IF(K61>14000,(K61*0.35)-2050)))))) -> 4986.2075 | M61: =F61*0.07 -> 1267.2415 | N61: =F61*0.11 -> 1991.3795 | P61: =L61+M61+O61 -> 6253.449 | Q61: 2000 | R61: =J61-P61+Q61 -> 15850.001
A62: 57 | B62: Meaza Getenet | C62: Distribution Officer | D62: Head Office | E62: 30 | F62: 22327.59 | G62: =+F62/30*E62 -> 22327.59 | I62: 7692.31 | J62: =G62+H62+I62 -> 30019.9 | K62: =G62+H62+I62 -> 30019.9 | L62: =IF(K62<=2000,(0),IF(K62<=4000,(K62*0.15)-300,IF(K62<=7000,(K62*0.2)-500,IF(K62<=10000,(K62*0.25)-850,IF(K62<=14000,(K62*0.3)-1350,IF(K62>14000,(K62*0.35)-2050)))))) -> 8456.965 | M62: =F62*0.07 -> 1562.9313 | N62: =F62*0.11 -> 2456.0349 | P62: =L62+M62+O62 -> 10019.896 | Q62: 2000 | R62: =J62-P62+Q62 -> 22000.004
A63: 58 | B63: Mekides Sime | C63: Finance mgr | D63: Head Office | E63: 30 | F63: 70603.45 | G63: =+F63/30*E63 -> 70603.45 | J63: =G63+H63+I63 -> 70603.45 | K63: =G63+H63+I63 -> 70603.45 | L63: =IF(K63<=2000,(0),IF(K63<=4000,(K63*0.15)-300,IF(K63<=7000,(K63*0.2)-500,IF(K63<=10000,(K63*0.25)-850,IF(K63<=14000,(K63*0.3)-1350,IF(K63>14000,(K63*0.35)-2050)))))) -> 22661.207 | M63: =F63*0.07 -> 4942.2415 | N63: =F63*0.11 -> 7766.3795 | P63: =L63+M63+O63 -> 27603.449 | R63: =J63-P63+Q63 -> 43000.001
A64: 59 | B64: Mekonin Siyum | C64: clurk | D64: Head Office | E64: 30 | F64: 8635.71 | G64: =+F64/30*E64 -> 8635.71 | J64: =G64+H64+I64 -> 8635.71 | K64: =G64+H64+I64 -> 8635.71 | L64: =IF(K64<=2000,(0),IF(K64<=4000,(K64*0.15)-300,IF(K64<=7000,(K64*0.2)-500,IF(K64<=10000,(K64*0.25)-850,IF(K64<=14000,(K64*0.3)-1350,IF(K64>14000,(K64*0.35)-2050)))))) -> 1308.9275 | P64: =L64+M64+O64 -> 1308.9275 | R64: =J64-P64+Q64 -> 7326.7825
A65: 60 | B65: Melkamu Tessema | C65: IT | D65: Head Office | E65: 30 | F65: 22307.69 | G65: =+F65/30*E65 -> 22307.69 | J65: =G65+H65+I65 -> 22307.69 | K65: =G65+H65+I65 -> 22307.69 | L65: =IF(K65<=2000,(0),IF(K65<=4000,(K65*0.15)-300,IF(K65<=7000,(K65*0.2)-500,IF(K65<=10000,(K65*0.25)-850,IF(K65<=14000,(K65*0.3)-1350,IF(K65>14000,(K65*0.35)-2050)))))) -> 5757.6915 | P65: =L65+M65+O65 -> 5757.6915 | Q65: 2000 | R65: =J65-P65+Q65 -> 18549.999
A66: 61 | B66: Mesfin Tesfaye | C66: GM | D66: Head Office | E66: 30 | F66: 125775.86 | G66: =+F66/30*E66 -> 125775.86 | J66: =G66+H66+I66 -> 125775.86 | K66: =G66+H66+I66 -> 125775.86 | L66: =IF(K66<=2000,(0),IF(K66<=4000,(K66*0.15)-300,IF(K66<=7000,(K66*0.2)-500,IF(K66<=10000,(K66*0.25)-850,IF(K66<=14000,(K66*0.3)-1350,IF(K66>14000,(K66*0.35)-2050)))))) -> 41971.551 | M66: =F66*0.07 -> 8804.3102 | N66: =F66*0.11 -> 13835.345 | P66: =L66+M66+O66 -> 50775.861 | R66: =J66-P66+Q66 -> 74999.999
A67: 62 | B67: Merima Degu | C67: Cleaner | D67: Abado | E67: 30 | F67: 2000 | G67: =+F67/30*E67 -> 2000 | J67: =G67+H67+I67 -> 2000 | K67: =G67+H67+I67 -> 2000 | L67: =IF(K67<=2000,(0),IF(K67<=4000,(K67*0.15)-300,IF(K67<=7000,(K67*0.2)-500,IF(K67<=10000,(K67*0.25)-850,IF(K67<=14000,(K67*0.3)-1350,IF(K67>14000,(K67*0.35)-2050)))))) -> 0 | P67: =L67+M67+O67 -> 0 | R67: =J67-P67+Q67 -> 2000
A68: 63 | B68: Mihret Atlabachew | C68: S.Accountant | D68: Abado | E68: 30 | F68: 9044.12 | G68: =+F68/30*E68 -> 9044.12 | I68: 2788.86 | J68: =G68+H68+I68 -> 11832.98 | K68: =G68+H68+I68 -> 11832.98 | L68: =IF(K68<=2000,(0),IF(K68<=4000,(K68*0.15)-300,IF(K68<=7000,(K68*0.2)-500,IF(K68<=10000,(K68*0.25)-850,IF(K68<=14000,(K68*0.3)-1350,IF(K68>14000,(K68*0.35)-2050)))))) -> 2199.894 | M68: =F68*0.07 -> 633.0884 | N68: =F68*0.11 -> 994.8532 | P68: =L68+M68+O68 -> 2832.9824 | Q68: =1000 -> 1000 | R68: =J68-P68+Q68 -> 9999.9976
A69: 64 | B69: Mintamir Ayele | C69: ASM | D69: Abado | E69: 30 | F69: 35344.83 | G69: =+F69/30*E69 -> 35344.83 | I69: =1846.15*0 -> 0 | J69: =G69+H69+I69 -> 35344.83 | K69: =G69+H69+I69 -> 35344.83 | L69: =IF(K69<=2000,(0),IF(K69<=4000,(K69*0.15)-300,IF(K69<=7000,(K69*0.2)-500,IF(K69<=10000,(K69*0.25)-850,IF(K69<=14000,(K69*0.3)-1350,IF(K69>14000,(K69*0.35)-2050)))))) -> 10320.691 | M69: =F69*0.07 -> 2474.1381 | N69: =F69*0.11 -> 3887.9313 | P69: =L69+M69+O69 -> 12794.829 | Q69: 2000 | R69: =J69-P69+Q69 -> 24550.001
A70: 65 | B70: Miraf Addisu | C70: S.Accountant | D70: BoleArabsa | E70: 13 | F70: 9044.12 | G70: =+F70/30*E70 -> 3919.1187 | I70: 2788.86 | J70: =G70+H70+I70 -> 6707.9787 | K70: =G70+H70+I70 -> 6707.9787 | L70: =IF(K70<=2000,(0),IF(K70<=4000,(K70*0.15)-300,IF(K70<=7000,(K70*0.2)-500,IF(K70<=10000,(K70*0.25)-850,IF(K70<=14000,(K70*0.3)-1350,IF(K70>14000,(K70*0.35)-2050)))))) -> 841.59573 | M70: =F70*0.07 -> 633.0884 | N70: =F70*0.11 -> 994.8532 | O70: 1000 | P70: =L70+M70+O70 -> 2474.6841 | Q70: 1000 | R70: =J70-P70+Q70 -> 5233.2945
A71: 66 | B71: Misganew Damte | C71: Security | D71: Ayat49 | E71: 30 | F71: 1000 | G71: =+F71/30*E71 -> 1000 | J71: =G71+H71+I71 -> 1000 | K71: =G71+H71+I71 -> 1000 | L71: =IF(K71<=2000,(0),IF(K71<=4000,(K71*0.15)-300,IF(K71<=7000,(K71*0.2)-500,IF(K71<=10000,(K71*0.25)-850,IF(K71<=14000,(K71*0.3)-1350,IF(K71>14000,(K71*0.35)-2050)))))) -> 0 | P71: =L71+M71+O71 -> 0 | R71: =J71-P71+Q71 -> 1000
A72: 67 | B72: Mitiku Kedit | C72: Security | D72: Megenagna | E72: 30 | F72: 1500 | G72: =+F72/30*E72 -> 1500 | J72: =G72+H72+I72 -> 1500 | K72: =G72+H72+I72 -> 1500 | L72: =IF(K72<=2000,(0),IF(K72<=4000,(K72*0.15)-300,IF(K72<=7000,(K72*0.2)-500,IF(K72<=10000,(K72*0.25)-850,IF(K72<=14000,(K72*0.3)-1350,IF(K72>14000,(K72*0.35)-2050)))))) -> 0 | P72: =L72+M72+O72 -> 0 | R72: =J72-P72+Q72 -> 1500
A73: 68 | B73: Mulunesh Hayanesh | C73: Cleaner | D73: H/mariam | E73: 30 | F73: 2820.51 | G73: =+F73/30*E73 -> 2820.51 | J73: =G73+H73+I73 -> 2820.51 | K73: =G73+H73+I73 -> 2820.51 | L73: =IF(K73<=2000,(0),IF(K73<=4000,(K73*0.15)-300,IF(K73<=7000,(K73*0.2)-500,IF(K73<=10000,(K73*0.25)-850,IF(K73<=14000,(K73*0.3)-1350,IF(K73>14000,(K73*0.35)-2050)))))) -> 123.0765 | M73: =F73*0.07 -> 197.4357 | N73: =F73*0.11 -> 310.2561 | P73: =L73+M73+O73 -> 320.5122 | R73: =J73-P73+Q73 -> 2499.9978
A74: 69 | B74: Rahel Abayneh | C74: DSP | D74: BoleArabsa | E74: 30 | F74: 7573.53 | G74: =+F74/30*E74 -> 7573.53 | I74: =2683.83/30*E74 -> 2683.83 | J74: =G74+H74+I74 -> 10257.36 | K74: =G74+H74+I74 -> 10257.36 | L74: =IF(K74<=2000,(0),IF(K74<=4000,(K74*0.15)-300,IF(K74<=7000,(K74*0.2)-500,IF(K74<=10000,(K74*0.25)-850,IF(K74<=14000,(K74*0.3)-1350,IF(K74>14000,(K74*0.35)-2050)))))) -> 1727.208 | M74: =F74*0.07 -> 530.1471 | N74: =F74*0.11 -> 833.0883 | P74: =L74+M74+O74 -> 2257.3551 | Q74: =1000/30*E74 -> 1000 | R74: =J74-P74+Q74 -> 9000.0049
A75: 70 | B75: Rahmet Kedir | C75: S.Accountant | D75: 6KILO | E75: 30 | F75: 9044.12 | G75: =+F75/30*E75 -> 9044.12 | I75: 2788.86 | J75: =G75+H75+I75 -> 11832.98 | K75: =G75+H75+I75 -> 11832.98 | L75: =IF(K75<=2000,(0),IF(K75<=4000,(K75*0.15)-300,IF(K75<=7000,(K75*0.2)-500,IF(K75<=10000,(K75*0.25)-850,IF(K75<=14000,(K75*0.3)-1350,IF(K75>14000,(K75*0.35)-2050)))))) -> 2199.894 | M75: =F75*0.07 -> 633.0884 | N75: =G75*0.11 -> 994.8532 | P75: =L75+M75+O75 -> 2832.9824 | Q75: 1000 | R75: =J75-P75+Q75 -> 9999.9976
A76: 71 | B76: Robel Siraw Kebede | C76: SM | D76: AyatTafo | E76: 30 | F76: 21724.14 | G76: =+F76/30*E76 -> 21724.14 | H76: 3000 | I76: =1846.15*0 -> 0 | J76: =G76+H76+I76 -> 24724.14 | K76: =G76+H76+I76 -> 24724.14 | L76: =IF(K76<=2000,(0),IF(K76<=4000,(K76*0.15)-300,IF(K76<=7000,(K76*0.2)-500,IF(K76<=10000,(K76*0.25)-850,IF(K76<=14000,(K76*0.3)-1350,IF(K76>14000,(K76*0.35)-2050)))))) -> 6603.449 | M76: =F76*0.07 -> 1520.6898 | N76: =F76*0.11 -> 2389.6554 | P76: =L76+M77+O76 -> 7133.5961 | Q76: =2000 -> 2000 | R76: =J76-P76+Q76 -> 19590.544
A77: 72 | B77: Rosa Alehegn | C77: DSP | D77: Kechene | E77: 30 | F77: 7573.53 | G77: =+F77/30*E77 -> 7573.53 | I77: =2683.83/30*E77 -> 2683.83 | J77: =G77+H77+I77 -> 10257.36 | K77: =G77+H77+I77 -> 10257.36 | L77: =IF(K77<=2000,(0),IF(K77<=4000,(K77*0.15)-300,IF(K77<=7000,(K77*0.2)-500,IF(K77<=10000,(K77*0.25)-850,IF(K77<=14000,(K77*0.3)-1350,IF(K77>14000,(K77*0.35)-2050)))))) -> 1727.208 | M77: =F77*0.07 -> 530.1471 | N77: =G77*0.11 -> 833.0883 | P77: =L77+M77+O77 -> 2257.3551 | Q77: =1000/30*E77 -> 1000 | R77: =J77-P77+Q77 -> 9000.0049
A78: 73 | B78: Samrawit Elias | C78: Device SV | D78: 4KILO | E78: 30 | F78: 11206.9 | G78: =+F78/30*E78 -> 11206.9 | I78: =3076.92*0.5 -> 1538.46 | J78: =G78+H78+I78 -> 12745.36 | K78: =G78+H78+I78 -> 12745.36 | L78: =IF(K78<=2000,(0),IF(K78<=4000,(K78*0.15)-300,IF(K78<=7000,(K78*0.2)-500,IF(K78<=10000,(K78*0.25)-850,IF(K78<=14000,(K78*0.3)-1350,IF(K78>14000,(K78*0.35)-2050)))))) -> 2473.608 | M78: =F78*0.07 -> 784.483 | N78: =F78*0.11 -> 1232.759 | P78: =L78+M78+O78 -> 3258.091 | R78: =J78-P78+Q78 -> 9487.269
A79: 74 | B79: Samrawit Mulugeta | C79: Accountant | D79: Head Office | E79: 30 | F79: 39568.97 | G79: =+F79/30*E79 -> 39568.97 | I79: 3076.92 | J79: =G79+H79+I79 -> 42645.89 | K79: =G79+H79+I79 -> 42645.89 | L79: =IF(K79<=2000,(0),IF(K79<=4000,(K79*0.15)-300,IF(K79<=7000,(K79*0.2)-500,IF(K79<=10000,(K79*0.25)-850,IF(K79<=14000,(K79*0.3)-1350,IF(K79>14000,(K79*0.35)-2050)))))) -> 12876.061 | M79: =F79*0.07 -> 2769.8279 | N79: =F79*0.11 -> 4352.5867 | P79: =L79+M79+O79 -> 15645.889 | Q79: 1500 | R79: =J79-P79+Q79 -> 28500.001
A80: 75 | B80: Samrawit Tekalgn | C80: ASM | D80: BoleArabsa | E80: 30 | F80: 35344.83 | G80: =+F80/30*E80 -> 35344.83 | I80: =1846.15*0 -> 0 | J80: =G80+H80+I80 -> 35344.83 | K80: =G80+H80+I80 -> 35344.83 | L80: =IF(K80<=2000,(0),IF(K80<=4000,(K80*0.15)-300,IF(K80<=7000,(K80*0.2)-500,IF(K80<=10000,(K80*0.25)-850,IF(K80<=14000,(K80*0.3)-1350,IF(K80>14000,(K80*0.35)-2050)))))) -> 10320.691 | M80: =F80*0.07 -> 2474.1381 | N80: =F80*0.11 -> 3887.9313 | P80: =L80+M80+O80 -> 12794.829 | Q80: 2000 | R80: =J80-P80+Q80 -> 24550.001
A81: 76 | B81: Seble Bejiga | C81: Finance | D81: Head Office | E81: 30 | F81: 23275.87 | G81: =+F81/30*E81 -> 23275.87 | J81: =G81+H81+I81 -> 23275.87 | K81: =G81+H81+I81 -> 23275.87 | L81: =IF(K81<=2000,(0),IF(K81<=4000,(K81*0.15)-300,IF(K81<=7000,(K81*0.2)-500,IF(K81<=10000,(K81*0.25)-850,IF(K81<=14000,(K81*0.3)-1350,IF(K81>14000,(K81*0.35)-2050)))))) -> 6096.5545 | M81: =F81*0.07 -> 1629.3109 | N81: =F81*0.11 -> 2560.3457 | P81: =L81+M81+O81 -> 7725.8654 | R81: =J81-P81+Q81 -> 15550.005
A82: 77 | B82: Setegn Argaw Bereka | C82: Shop SV | D82: H/mariam | E82: 30 | F82: 17155.18 | G82: =+F82/30*E82 -> 17155.18 | I82: =1846.15*0 -> 0 | J82: =G82+H82+I82 -> 17155.18 | K82: =G82+H82+I82 -> 17155.18 | L82: =IF(K82<=2000,(0),IF(K82<=4000,(K82*0.15)-300,IF(K82<=7000,(K82*0.2)-500,IF(K82<=10000,(K82*0.25)-850,IF(K82<=14000,(K82*0.3)-1350,IF(K82>14000,(K82*0.35)-2050)))))) -> 3954.313 | P82: =L82+M82+O82 -> 3954.313 | Q82: 1000 | R82: =J82-P82+Q82 -> 14200.867
A83: 78 | B83: Selam Ashenafi | C83: CEO coordinator | D83: Head Office | E83: 30 | F83: 65431.03 | G83: =+F83/30*E83 -> 65431.03 | J83: =G83+H83+I83 -> 65431.03 | K83: =G83+H83+I83 -> 65431.03 | L83: =IF(K83<=2000,(0),IF(K83<=4000,(K83*0.15)-300,IF(K83<=7000,(K83*0.2)-500,IF(K83<=10000,(K83*0.25)-850,IF(K83<=14000,(K83*0.3)-1350,IF(K83>14000,(K83*0.35)-2050)))))) -> 20850.861 | M83: =F83*0.07 -> 4580.1721 | P83: =L83+M83+O83 -> 25431.033 | R83: =J83-P83+Q83 -> 39999.997
A84: 79 | B84: Selam Getachew | C84: SM | D84: Kara | E84: 30 | F84: 21724.14 | G84: =+F84/30*E84 -> 21724.14 | H84: =6463+12403 -> 18866 | I84: =1846.15*0 -> 0 | J84: =G84+H84+I84 -> 40590.14 | K84: =G84+H84+I84 -> 40590.14 | L84: =IF(K84<=2000,(0),IF(K84<=4000,(K84*0.15)-300,IF(K84<=7000,(K84*0.2)-500,IF(K84<=10000,(K84*0.25)-850,IF(K84<=14000,(K84*0.3)-1350,IF(K84>14000,(K84*0.35)-2050)))))) -> 12156.549 | M84: =F84*0.07 -> 1520.6898 | N84: =F84*0.11 -> 2389.6554 | P84: =L84+M84+O84 -> 13677.239 | Q84: =2000 -> 2000 | R84: =J84-P84+Q84 -> 28912.901
A85: 80 | B85: Selamawit Million | C85: ASM | D85: 6KILO | E85: 30 | F85: 35344.83 | G85: =+F85/30*E85 -> 35344.83 | H85: =3400+1600 -> 5000 | I85: =1846.15*0 -> 0 | J85: =G85+H85+I85 -> 40344.83 | K85: =G85+H85+I85 -> 40344.83 | L85: =IF(K85<=2000,(0),IF(K85<=4000,(K85*0.15)-300,IF(K85<=7000,(K85*0.2)-500,IF(K85<=10000,(K85*0.25)-850,IF(K85<=14000,(K85*0.3)-1350,IF(K85>14000,(K85*0.35)-2050)))))) -> 12070.691 | M85: =F85*0.07 -> 2474.1381 | N85: =F85*0.11 -> 3887.9313 | P85: =L85+M85+O85 -> 14544.829 | Q85: 2000 | R85: =J85-P85+Q85 -> 27800.001
A86: 81 | B86: Selamawit Tesfaye | C86: S.Accountant | D86: Ferencai | E86: 30 | F86: 9044.12 | G86: =+F86/30*E86 -> 9044.12 | I86: 2788.86 | J86: =G86+H86+I86 -> 11832.98 | K86: =G86+H86+I86 -> 11832.98 | L86: =IF(K86<=2000,(0),IF(K86<=4000,(K86*0.15)-300,IF(K86<=7000,(K86*0.2)-500,IF(K86<=10000,(K86*0.25)-850,IF(K86<=14000,(K86*0.3)-1350,IF(K86>14000,(K86*0.35)-2050)))))) -> 2199.894 | M86: =F86*0.07 -> 633.0884 | N86: =F86*0.11 -> 994.8532 | P86: =L86+M86+O86 -> 2832.9824 | Q86: 1000 | R86: =J86-P86+Q86 -> 9999.9976
A87: 82 | B87: Selamawit Wagnew Berbew | C87: Shop SV | D87: 6KILO | E87: 30 | F87: 17155.18 | G87: =+F87/30*E87 -> 17155.18 | I87: =1846.15*0 -> 0 | J87: =G87+H87+I87 -> 17155.18 | K87: =G87+H87+I87 -> 17155.18 | L87: =IF(K87<=2000,(0),IF(K87<=4000,(K87*0.15)-300,IF(K87<=7000,(K87*0.2)-500,IF(K87<=10000,(K87*0.25)-850,IF(K87<=14000,(K87*0.3)-1350,IF(K87>14000,(K87*0.35)-2050)))))) -> 3954.313 | M87: =F87*0.07 -> 1200.8626 | N87: =F87*0.11 -> 1887.0698 | P87: =L87+M87+O87 -> 5155.1756 | Q87: =1000/30*E87 -> 1000 | R87: =J87-P87+Q87 -> 13000.004
A88: 83 | B88: Senait Fikremariam | C88: DSP | D88: Shiromeda | E88: 30 | F88: 7573.53 | G88: =+F88/30*E88 -> 7573.53 | I88: =3076.92 -> 3076.92 | J88: =G88+H88+I88 -> 10650.45 | K88: =G88+H88+I88 -> 10650.45 | L88: =IF(K88<=2000,(0),IF(K88<=4000,(K88*0.15)-300,IF(K88<=7000,(K88*0.2)-500,IF(K88<=10000,(K88*0.25)-850,IF(K88<=14000,(K88*0.3)-1350,IF(K88>14000,(K88*0.35)-2050)))))) -> 1845.135 | M88: =F88*0.07 -> 530.1471 | N88: =F88*0.11 -> 833.0883 | P88: =L88+M88+O88 -> 2375.2821 | Q88: 1000 | R88: =J88-P88+Q88 -> 9275.1679
A89: 84 | B89: Serkalem Moga | C89: Cleaner | D89: Fiyelbet | E89: 30 | F89: 3371.88 | G89: =+F89/30*E89 -> 3371.88 | I89: =1846.15*'[1]Shop Mgr KPI'!F7 -> 0 | J89: =G89+H89+I89 -> 3371.88 | K89: =G89+H89+I89 -> 3371.88 | L89: =IF(K89<=2000,(0),IF(K89<=4000,(K89*0.15)-300,IF(K89<=7000,(K89*0.2)-500,IF(K89<=10000,(K89*0.25)-850,IF(K89<=14000,(K89*0.3)-1350,IF(K89>14000,(K89*0.35)-2050)))))) -> 205.782 | M89: =F89*0.07 -> 236.0316 | N89: =F89*0.11 -> 370.9068 | P89: =L89+M89+O89 -> 441.8136 | R89: =J89-P89+Q89 -> 2930.0664
A90: 85 | B90: Shemsu Kedir | C90: ASM | D90: AyatTafo | E90: 30 | F90: 35344.83 | G90: =+F90/30*E90 -> 35344.83 | I90: =1846.15*0 -> 0 | J90: =G90+H90+I90 -> 35344.83 | K90: =G90+H90+I90 -> 35344.83 | L90: =IF(K90<=2000,(0),IF(K90<=4000,(K90*0.15)-300,IF(K90<=7000,(K90*0.2)-500,IF(K90<=10000,(K90*0.25)-850,IF(K90<=14000,(K90*0.3)-1350,IF(K90>14000,(K90*0.35)-2050)))))) -> 10320.691 | M90: =F90*0.07 -> 2474.1381 | N90: =F90*0.11 -> 3887.9313 | P90: =L90+M90+O90 -> 12794.829 | Q90: 2000 | R90: =J90-P90+Q90 -> 24550.001
A91: 86 | B91: Shetu Bahru | C91: Cleaner | D91: Shiromeda | E91: 30 | F91: 1600 | G91: =+F91/30*E91 -> 1600 | J91: =G91+H91+I91 -> 1600 | K91: =G91+H91+I91 -> 1600 | L91: =IF(K91<=2000,(0),IF(K91<=4000,(K91*0.15)-300,IF(K91<=7000,(K91*0.2)-500,IF(K91<=10000,(K91*0.25)-850,IF(K91<=14000,(K91*0.3)-1350,IF(K91>14000,(K91*0.35)-2050)))))) -> 0 | M91: =F91*0.07 -> 112 | N91: =F91*0.11 -> 176 | P91: =L91+M91+O91 -> 112 | R91: =J91-P91+Q91 -> 1488
A92: 87 | B92: Simegn Ashebir | C92: S.Accountant | D92: Kara | E92: 30 | F92: 9595.24 | G92: =+F92/30*E92 -> 9595.24 | I92: 2976.55 | J92: =G92+H92+I92 -> 12571.79 | K92: =G92+H92+I92 -> 12571.79 | L92: =IF(K92<=2000,(0),IF(K92<=4000,(K92*0.15)-300,IF(K92<=7000,(K92*0.2)-500,IF(K92<=10000,(K92*0.25)-850,IF(K92<=14000,(K92*0.3)-1350,IF(K92>14000,(K92*0.35)-2050)))))) -> 2421.537 | M92: =F92*0.07 -> 671.6668 | N92: =F92*0.11 -> 1055.4764 | P92: =L92+M92+O92 -> 3093.2038 | Q92: 1000 | R92: =J92-P92+Q92 -> 10478.586
A93: 88 | B93: Sisay Dereje | C93: Cleaner | D93: Kechene | E93: 30 | F93: 1612.9 | G93: =+F93/30*E93 -> 1612.9 | J93: =G93+H93+I93 -> 1612.9 | K93: =G93+H93+I93 -> 1612.9 | L93: =IF(K93<=2000,(0),IF(K93<=4000,(K93*0.15)-300,IF(K93<=7000,(K93*0.2)-500,IF(K93<=10000,(K93*0.25)-850,IF(K93<=14000,(K93*0.3)-1350,IF(K93>14000,(K93*0.35)-2050)))))) -> 0 | P93: =L93+M93+O93 -> 0 | R93: =J93-P93+Q93 -> 1612.9
A94: 89 | B94: Solomon Million | C94: DSP | D94: AyatTafo | E94: 30 | F94: 9729.07 | G94: =+F94/30*E94 -> 9729.07 | I94: =2857.14 -> 2857.14 | J94: =G94+H94+I94 -> 12586.21 | K94: =G94+H94+I94 -> 12586.21 | L94: =IF(K94<=2000,(0),IF(K94<=4000,(K94*0.15)-300,IF(K94<=7000,(K94*0.2)-500,IF(K94<=10000,(K94*0.25)-850,IF(K94<=14000,(K94*0.3)-1350,IF(K94>14000,(K94*0.35)-2050)))))) -> 2425.863 | M94: =F94*0.07 -> 681.0349 | N94: =F94*0.11 -> 1070.1977 | P94: =L94+M94+O94 -> 3106.8979 | Q94: =1000/30*E94+370 -> 1370 | R94: =J94-P94+Q94 -> 10849.312
A95: 90 | B95: Tebarek Bargicho | C95: sales operation | D95: Head Office | E95: 30 | F95: 62931.03 | G95: =+F95/30*E95 -> 62931.03 | I95: =10769.23*0 -> 0 | J95: =G95+H95+I95 -> 62931.03 | K95: =G95+H95+I95 -> 62931.03 | L95: =IF(K95<=2000,(0),IF(K95<=4000,(K95*0.15)-300,IF(K95<=7000,(K95*0.2)-500,IF(K95<=10000,(K95*0.25)-850,IF(K95<=14000,(K95*0.3)-1350,IF(K95>14000,(K95*0.35)-2050)))))) -> 19975.86 | M95: =F95*0.07 -> 4405.1721 | N95: =F95*0.11 -> 6922.4133 | P95: =L95+M95+O95 -> 24381.033 | Q95: 3000 | R95: =J95-P95+Q95 -> 41549.997
A96: 91 | B96: Tarekegn Ameru | C96: BA coordinator | D96: Fiyelbet | E96: 30 | F96: 4794.52 | G96: =+F96/30*E96 -> 4794.52 | I96: =2519.64/30*E96 -> 2519.64 | J96: =G96+H96+I96 -> 7314.16 | K96: =G96+H96+I96 -> 7314.16 | L96: =IF(K96<=2000,(0),IF(K96<=4000,(K96*0.15)-300,IF(K96<=7000,(K96*0.2)-500,IF(K96<=10000,(K96*0.25)-850,IF(K96<=14000,(K96*0.3)-1350,IF(K96>14000,(K96*0.35)-2050)))))) -> 978.54 | M96: =F96*0.07 -> 335.6164 | N96: =F96*0.11 -> 527.3972 | P96: =L96+M96+O96 -> 1314.1564 | Q96: 1000 | R96: =J96-P96+Q96 -> 7000.0036
A97: 92 | B97: Tesefaye Hunachew | C97: DSP | D97: Abado | E97: 30 | F97: 7573.53 | G97: =+F97/30*E97 -> 7573.53 | I97: =2683.83/30*E97 -> 2683.83 | J97: =G97+H97+I97 -> 10257.36 | K97: =G97+H97+I97 -> 10257.36 | L97: =IF(K97<=2000,(0),IF(K97<=4000,(K97*0.15)-300,IF(K97<=7000,(K97*0.2)-500,IF(K97<=10000,(K97*0.25)-850,IF(K97<=14000,(K97*0.3)-1350,IF(K97>14000,(K97*0.35)-2050)))))) -> 1727.208 | M97: =F97*0.07 -> 530.1471 | N97: =F97*0.11 -> 833.0883 | P97: =L97+M97+O97 -> 2257.3551 | Q97: =1000+1480 -> 2480 | R97: =J97-P97+Q97 -> 10480.005
A98: 93 | B98: Tesfaye Sisay | C98: SM | D98: Ferencai | E98: 30 | F98: 21724.14 | G98: =+F98/30*E98 -> 21724.14 | H98: 8043 | I98: =1846.15*0 -> 0 | J98: =G98+H98+I98 -> 29767.14 | K98: =G98+H98+I98 -> 29767.14 | L98: =IF(K98<=2000,(0),IF(K98<=4000,(K98*0.15)-300,IF(K98<=7000,(K98*0.2)-500,IF(K98<=10000,(K98*0.25)-850,IF(K98<=14000,(K98*0.3)-1350,IF(K98>14000,(K98*0.35)-2050)))))) -> 8368.499 | M98: =F98*0.07 -> 1520.6898 | N98: =F98*0.11 -> 2389.6554 | P98: =L98+M98+O98 -> 9889.1888 | Q98: 2000 | R98: =J98-P98+Q98 -> 21877.951
A99: 94 | B99: Teshome Yalew | C99: SM | D99: Megenagna | E99: 30 | F99: 21724.14 | G99: =+F99/30*E99 -> 21724.14 | H99: 4000 | I99: =1846.15*0 -> 0 | J99: =G99+H99+I99 -> 25724.14 | K99: =G99+H99+I99 -> 25724.14 | L99: =IF(K99<=2000,(0),IF(K99<=4000,(K99*0.15)-300,IF(K99<=7000,(K99*0.2)-500,IF(K99<=10000,(K99*0.25)-850,IF(K99<=14000,(K99*0.3)-1350,IF(K99>14000,(K99*0.35)-2050)))))) -> 6953.449 | M99: =F99*0.07 -> 1520.6898 | N99: =F99*0.11 -> 2389.6554 | P99: =L99+M99+O99 -> 8474.1388 | Q99: =2000 -> 2000 | R99: =J99-P99+Q99 -> 19250.001
A100: 95 | B100: Tewdros Ayanaw | C100: BA coordinator | D100: 6KILO | E100: 30 | F100: 4794.52 | G100: =+F100/30*E100 -> 4794.52 | I100: =2519.64/30*E100 -> 2519.64 | J100: =G100+H100+I100 -> 7314.16 | K100: =G100+H100+I100 -> 7314.16 | L100: =IF(K100<=2000,(0),IF(K100<=4000,(K100*0.15)-300,IF(K100<=7000,(K100*0.2)-500,IF(K100<=10000,(K100*0.25)-850,IF(K100<=14000,(K100*0.3)-1350,IF(K100>14000,(K100*0.35)-2050)))))) -> 978.54 | P100: =L100+M100+O100 -> 978.54 | Q100: 1000 | R100: =J100-P100+Q100 -> 7335.62
A101: 96 | B101: Tewodros Tadesse Yimer | C101: Driver | D101: Head Office | E101: 30 | F101: 14655.17 | G101: =+F101/30*E101 -> 14655.17 | H101: =7692.3/30*E101 -> 7692.3 | I101: =3076.93/30*E101 -> 3076.93 | J101: =G101+H101+I101 -> 25424.4 | K101: =G101+H101+I101 -> 25424.4 | L101: =IF(K101<=2000,(0),IF(K101<=4000,(K101*0.15)-300,IF(K101<=7000,(K101*0.2)-500,IF(K101<=10000,(K101*0.25)-850,IF(K101<=14000,(K101*0.3)-1350,IF(K101>14000,(K101*0.35)-2050)))))) -> 6848.54 | M101: =F101*0.07 -> 1025.8619 | N101: =F101*0.11 -> 1612.0687 | P101: =L101+M101+O101 -> 7874.4019 | Q101: =1000+1000 -> 2000 | R101: =J101-P101+Q101 -> 19549.998
...

Sheet DSA
A1: LeapFrog Software Technology Africa PLC
A2: Payroll Sheet DSA Staff
A3: For the Month of Sene 2018
A4: No. | B4: Name of Employees | C4: Position | D4: Shop Name | E4: Working days | F4: Basic Salary | G4: Monthly Salary | H4: Commiss. /OT | I4: KPI | J4: Gross Salary | K4: Taxable Income | L4: Income Tax | M4: Pension 7% | N4: Pension 11% | O4: Shortage/ Loan | P4: Total Deduction | Q4: Transport & other allowance | R4: Net Pay | S4: sign
A5: 1 | B5: Abdi Sultan | C5: DSA Coordinator | D5: Ferencai | E5: 30 | F5: 9044.12 | G5: =+F5/30*E5 -> 9044.12 | H5: =4088+3858+3631 -> 11577 | I5: =2788.86 -> 2788.86 | J5: =G5+H5+I5 -> 23409.98 | K5: =G5+H5+I5 -> 23409.98 | L5: =IF(K5<=2000,(0),IF(K5<=4000,(K5*0.15)-300,IF(K5<=7000,(K5*0.2)-500,IF(K5<=10000,(K5*0.25)-850,IF(K5<=14000,(K5*0.3)-1350,IF(K5>14000,(K5*0.35)-2050)))))) -> 6143.493 | M5: =F5*0.07 -> 633.0884 | N5: =F5*0.11 -> 994.8532 | P5: =L5+M5+O5 -> 6776.5814 | Q5: 1500 | R5: =J5-P5+Q5 -> 18133.399
A6: 3 | B6: Adino Moges | C6: DSA Coordinator | D6: Shiromeda | E6: 30 | F6: 9044.12 | G6: =+F6/30*E6 -> 9044.12 | H6: 2393 | I6: =2788.86*0.5 -> 1394.43 | J6: =G6+H6+I6 -> 12831.55 | K6: =G6+H6+I6 -> 12831.55 | L6: =IF(K6<=2000,(0),IF(K6<=4000,(K6*0.15)-300,IF(K6<=7000,(K6*0.2)-500,IF(K6<=10000,(K6*0.25)-850,IF(K6<=14000,(K6*0.3)-1350,IF(K6>14000,(K6*0.35)-2050)))))) -> 2499.465 | M6: =F6*0.07 -> 633.0884 | N6: =F6*0.11 -> 994.8532 | P6: =L6+M6+O6 -> 3132.5534 | Q6: 1500 | R6: =J6-P6+Q6 -> 11198.997
A7: 5 | B7: Ayele Getahun | C7: DSA Coordinator | D7: BoleArabsa | E7: 30 | F7: 9044.12 | G7: =+F7/30*E7 -> 9044.12 | H7: =14260+8984 -> 23244 | I7: =2788.86 -> 2788.86 | J7: =G7+H7+I7 -> 35076.98 | K7: =G7+H7+I7 -> 35076.98 | L7: =IF(K7<=2000,(0),IF(K7<=4000,(K7*0.15)-300,IF(K7<=7000,(K7*0.2)-500,IF(K7<=10000,(K7*0.25)-850,IF(K7<=14000,(K7*0.3)-1350,IF(K7>14000,(K7*0.35)-2050)))))) -> 10226.943 | M7: =F7*0.07 -> 633.0884 | N7: =F7*0.11 -> 994.8532 | P7: =L7+M7+O7 -> 10860.031 | Q7: 1500 | R7: =J7-P7+Q7 -> 25716.949
A8: 6 | B8: Azazhu Gashaw | C8: DSA | D8: 4KILO | E8: 30 | F8: 9044.12 | G8: =+F8/30*E8 -> 9044.12 | H8: =3245+5462 -> 8707 | I8: =2788.86*0.5 -> 1394.43 | J8: =G8+H8+I8 -> 19145.55 | K8: =G8+H8+I8 -> 19145.55 | L8: =IF(K8<=2000,(0),IF(K8<=4000,(K8*0.15)-300,IF(K8<=7000,(K8*0.2)-500,IF(K8<=10000,(K8*0.25)-850,IF(K8<=14000,(K8*0.3)-1350,IF(K8>14000,(K8*0.35)-2050)))))) -> 4650.9425 | M8: =F8*0.07 -> 633.0884 | N8: =F8*0.11 -> 994.8532 | P8: =L8+M8+O8 -> 5284.0309 | Q8: 1500 | R8: =J8-P8+Q8 -> 15361.519
A9: 7 | B9: Belaynew Tesfa | C9: DSA | D9: AyatTafo | E9: 30 | F9: 9044.12 | G9: =+F9/30*E9 -> 9044.12 | H9: =5491+5190 -> 10681 | I9: =2788.86*0.5 -> 1394.43 | J9: =G9+H9+I9 -> 21119.55 | K9: =G9+H9+I9 -> 21119.55 | L9: =IF(K9<=2000,(0),IF(K9<=4000,(K9*0.15)-300,IF(K9<=7000,(K9*0.2)-500,IF(K9<=10000,(K9*0.25)-850,IF(K9<=14000,(K9*0.3)-1350,IF(K9>14000,(K9*0.35)-2050)))))) -> 5341.8425 | M9: =F9*0.07 -> 633.0884 | N9: =F9*0.11 -> 994.8532 | P9: =L9+M9+O9 -> 5974.9309 | Q9: 1500 | R9: =J9-P9+Q9 -> 16644.619
A10: 10 | B10: Biruk Asmare | C10: DSA Coordinator | D10: Meri AYAT | E10: 30 | F10: 9044.12 | G10: =+F10/30*E10 -> 9044.12 | H10: =2803+4959 -> 7762 | I10: =2788.86*0.5 -> 1394.43 | J10: =G10+H10+I10 -> 18200.55 | K10: =G10+H10+I10 -> 18200.55 | L10: =IF(K10<=2000,(0),IF(K10<=4000,(K10*0.15)-300,IF(K10<=7000,(K10*0.2)-500,IF(K10<=10000,(K10*0.25)-850,IF(K10<=14000,(K10*0.3)-1350,IF(K10>14000,(K10*0.35)-2050)))))) -> 4320.1925 | M10: =F10*0.07 -> 633.0884 | N10: =F10*0.11 -> 994.8532 | P10: =L10+M10+O10 -> 4953.2809 | Q10: 1500 | R10: =J10-P10+Q10 -> 14747.269
A11: 11 | B11: Getachew Altaseb | C11: DSA | D11: 6KILO | E11: 30 | F11: 9044.12 | G11: =+F11/30*E11 -> 9044.12 | H11: =1748+3357 -> 5105 | J11: =G11+H11+I11 -> 14149.12 | K11: =G11+H11+I11 -> 14149.12 | L11: =IF(K11<=2000,(0),IF(K11<=4000,(K11*0.15)-300,IF(K11<=7000,(K11*0.2)-500,IF(K11<=10000,(K11*0.25)-850,IF(K11<=14000,(K11*0.3)-1350,IF(K11>14000,(K11*0.35)-2050)))))) -> 2902.192 | P11: =L11+M11+O11 -> 2902.192 | R11: =J11-P11+Q11 -> 11246.928
A12: 12 | B12: Habtamu Shewaye | C12: DSA Coordinator | D12: Kara | E12: 24 | F12: 9044.12 | G12: =+F12/30*E12 -> 7235.296 | H12: =7373+4580 -> 11953 | I12: =2788.86*0.5 -> 1394.43 | J12: =G12+H12+I12 -> 20582.726 | K12: =G12+H12+I12 -> 20582.726 | L12: =IF(K12<=2000,(0),IF(K12<=4000,(K12*0.15)-300,IF(K12<=7000,(K12*0.2)-500,IF(K12<=10000,(K12*0.25)-850,IF(K12<=14000,(K12*0.3)-1350,IF(K12>14000,(K12*0.35)-2050)))))) -> 5153.9541 | M12: =F12*0.07 -> 633.0884 | N12: =F12*0.11 -> 994.8532 | P12: =L12+M12+O12 -> 5787.0425 | Q12: 1500 | R12: =J12-P12+Q12 -> 16295.684
A13: 13 | B13: Hassen Seid | C13: DSA | D13: Head Office | E13: 30 | F13: 8007.94 | G13: =+F13/30*E13 -> 8007.94 | I13: 2519.64 | J13: =G13+H13+I13 -> 10527.58 | K13: =G13+H13+I13 -> 10527.58 | L13: =IF(K13<=2000,(0),IF(K13<=4000,(K13*0.15)-300,IF(K13<=7000,(K13*0.2)-500,IF(K13<=10000,(K13*0.25)-850,IF(K13<=14000,(K13*0.3)-1350,IF(K13>14000,(K13*0.35)-2050)))))) -> 1808.274 | M13: =F13*0.07 -> 560.5558 | N13: =F13*0.11 -> 880.8734 | P13: =L13+M13+O13 -> 2368.8298 | Q13: 1000 | R13: =J13-P13+Q13 -> 9158.7502
A14: 15 | B14: Lelise Melkam | C14: DSA | D14: BoleArabsa | E14: 30 | F14: 4794.52 | G14: =+F14/30*E14 -> 4794.52 | I14: =2519.64 -> 2519.64 | J14: =G14+H14+I14 -> 7314.16 | K14: =G14+H14+I14 -> 7314.16 | L14: =IF(K14<=2000,(0),IF(K14<=4000,(K14*0.15)-300,IF(K14<=7000,(K14*0.2)-500,IF(K14<=10000,(K14*0.25)-850,IF(K14<=14000,(K14*0.3)-1350,IF(K14>14000,(K14*0.35)-2050)))))) -> 978.54 | M14: =F14*0.07 -> 335.6164 | N14: =F14*0.11 -> 527.3972 | P14: =L14+M14+O14 -> 1314.1564 | Q14: 1000 | R14: =J14-P14+Q14 -> 7000.0036
A15: 18 | B15: Mihret Worku | C15: DSA | D15: Summit | E15: 7 | F15: 9045.12 | G15: =+F15/30*E15 -> 2110.528 | J15: =G15+H15+I15 -> 2110.528 | K15: =G15+H15+I15 -> 2110.528 | L15: =IF(K15<=2000,(0),IF(K15<=4000,(K15*0.15)-300,IF(K15<=7000,(K15*0.2)-500,IF(K15<=10000,(K15*0.25)-850,IF(K15<=14000,(K15*0.3)-1350,IF(K15>14000,(K15*0.35)-2050)))))) -> 16.5792 | P15: =L15+M15+O15 -> 16.5792 | R15: =J15-P15+Q15 -> 2093.9488
A16: 21 | B16: Samuel Tesfaye | C16: DSA | D16: AYAT49 | E16: 30 | F16: 9044.12 | G16: =+F16/30*E16 -> 9044.12 | H16: =2735+2692 -> 5427 | I16: =2788.86*0.5 -> 1394.43 | J16: =G16+H16+I16 -> 15865.55 | K16: =G16+H16+I16 -> 15865.55 | L16: =IF(K16<=2000,(0),IF(K16<=4000,(K16*0.15)-300,IF(K16<=7000,(K16*0.2)-500,IF(K16<=10000,(K16*0.25)-850,IF(K16<=14000,(K16*0.3)-1350,IF(K16>14000,(K16*0.35)-2050)))))) -> 3502.9425 | M16: =F16*0.07 -> 633.0884 | N16: =F16*0.11 -> 994.8532 | P16: =L16+M16+O16 -> 4136.0309 | Q16: 1500 | R16: =J16-P16+Q16 -> 13229.519
A17: 22 | B17: Sekina Hassen | C17: DSA | D17: Kara | E17: 30 | F17: 4794.52 | G17: =+F17/30*E17 -> 4794.52 | H17: ='Performance Summary'!K4 -> 3249.81 | I17: =2519.64 -> 2519.64 | J17: =G17+H17+I17 -> 10563.97 | K17: =G17+H17+I17 -> 10563.97 | L17: =IF(K17<=2000,(0),IF(K17<=4000,(K17*0.15)-300,IF(K17<=7000,(K17*0.2)-500,IF(K17<=10000,(K17*0.25)-850,IF(K17<=14000,(K17*0.3)-1350,IF(K17>14000,(K17*0.35)-2050)))))) -> 1819.191 | M17: =F17*0.07 -> 335.6164 | N17: =F17*0.11 -> 527.3972 | P17: =L17+M17+O17 -> 2154.8074 | Q17: 1000 | R17: =J17-P17+Q17 -> 9409.1626
A18: 23 | B18: Solomon Dessie | C18: DSA | D18: H/mariam | E18: 30 | F18: 4794.52 | G18: =+F18/30*E18 -> 4794.52 | I18: =2519.64 -> 2519.64 | J18: =G18+H18+I18 -> 7314.16 | K18: =G18+H18+I18 -> 7314.16 | L18: =IF(K18<=2000,(0),IF(K18<=4000,(K18*0.15)-300,IF(K18<=7000,(K18*0.2)-500,IF(K18<=10000,(K18*0.25)-850,IF(K18<=14000,(K18*0.3)-1350,IF(K18>14000,(K18*0.35)-2050)))))) -> 978.54 | M18: =F18*0.07 -> 335.6164 | N18: =F18*0.11 -> 527.3972 | P18: =L18+M18+O18 -> 1314.1564 | Q18: 1000 | R18: =J18-P18+Q18 -> 7000.0036
A19: 24 | B19: Tigist Gedif | C19: DSA | D19: BoleArabsa | E19: 30 | F19: 9044.12 | G19: =+F19/30*E19 -> 9044.12 | H19: =281+5231 -> 5512 | I19: =2788.86 -> 2788.86 | J19: =G19+H19+I19 -> 17344.98 | K19: =G19+H19+I19 -> 17344.98 | L19: =IF(K19<=2000,(0),IF(K19<=4000,(K19*0.15)-300,IF(K19<=7000,(K19*0.2)-500,IF(K19<=10000,(K19*0.25)-850,IF(K19<=14000,(K19*0.3)-1350,IF(K19>14000,(K19*0.35)-2050)))))) -> 4020.743 | M19: =F19*0.07 -> 633.0884 | N19: =F19*0.11 -> 994.8532 | P19: =L19+M19+O19 -> 4653.8314 | Q19: 1500 | R19: =J19-P19+Q19 -> 14191.149
A20: 27 | B20: Deribe Nigussie | C20: DSA | D20: Aleltu | E20: 30 | F20: 6164.38 | G20: =+F20/30*E20 -> 6164.38 | H20: =7313+4857 -> 12170 | I20: 2610.96 | J20: =G20+H20+I20 -> 20945.34 | K20: =G20+H20+I20 -> 20945.34 | L20: =IF(K20<=2000,(0),IF(K20<=4000,(K20*0.15)-300,IF(K20<=7000,(K20*0.2)-500,IF(K20<=10000,(K20*0.25)-850,IF(K20<=14000,(K20*0.3)-1350,IF(K20>14000,(K20*0.35)-2050)))))) -> 5280.869 | M20: =F20*0.07 -> 431.5066 | N20: =F20*0.11 -> 678.0818 | P20: =L20+M20+O20 -> 5712.3756 | Q20: 1500 | R20: =J20-P20+Q20 -> 16732.964
A21: 28 | B21: Gete Getahun | C21: DSA | D21: Chacha | E21: 30 | F21: 6164.38 | G21: =+F21/30*E21 -> 6164.38 | H21: =9434+4689 -> 14123 | I21: 2610.96 | J21: =G21+H21+I21 -> 22898.34 | K21: =G21+H21+I21 -> 22898.34 | L21: =IF(K21<=2000,(0),IF(K21<=4000,(K21*0.15)-300,IF(K21<=7000,(K21*0.2)-500,IF(K21<=10000,(K21*0.25)-850,IF(K21<=14000,(K21*0.3)-1350,IF(K21>14000,(K21*0.35)-2050)))))) -> 5964.419 | M21: =F21*0.07 -> 431.5066 | N21: =F21*0.11 -> 678.0818 | P21: =L21+M21+O21 -> 6395.9256 | Q21: 1500 | R21: =J21-P21+Q21 -> 18002.414
A22: 29 | B22: Moges Nigusu | C22: DSA | D22: Chacha | E22: 8 | F22: 6164.38 | G22: =+F22/30*E22 -> 1643.8347 | H22: =2074 -> 2074 | I22: =1277.63*0 -> 0 | J22: =G22+H22+I22 -> 3717.8347 | K22: =G22+H22+I22 -> 3717.8347 | L22: =IF(K22<=2000,(0),IF(K22<=4000,(K22*0.15)-300,IF(K22<=7000,(K22*0.2)-500,IF(K22<=10000,(K22*0.25)-850,IF(K22<=14000,(K22*0.3)-1350,IF(K22>14000,(K22*0.35)-2050)))))) -> 257.6752 | M22: =F22*0.07 -> 431.5066 | N22: =F22*0.11 -> 678.0818 | P22: =L22+M22+O22 -> 689.1818 | Q22: =1500*0 -> 0 | R22: =J22-P22+Q22 -> 3028.6529
A23: 30 | B23: Teka Dejene | C23: DSA | D23: Chacha | E23: 30 | F23: 6164.38 | G23: =+F23/30*E23 -> 6164.38 | H23: 4685 | I23: 2610.96 | J23: =G23+H23+I23 -> 13460.34 | K23: =G23+H23+I23 -> 13460.34 | L23: =IF(K23<=2000,(0),IF(K23<=4000,(K23*0.15)-300,IF(K23<=7000,(K23*0.2)-500,IF(K23<=10000,(K23*0.25)-850,IF(K23<=14000,(K23*0.3)-1350,IF(K23>14000,(K23*0.35)-2050)))))) -> 2688.102 | P23: =L23+M23+O23 -> 2688.102 | Q23: 1500 | R23: =J23-P23+Q23 -> 12272.238
A24: 31 | B24: Eshetu Zewde | C24: DSA | D24: Tafo Mission | E24: 30 | F24: 9044.12 | G24: =+F24/30*E24 -> 9044.12 | H24: =7534+7184 -> 14718 | I24: =2788.86 -> 2788.86 | J24: =G24+H24+I24 -> 26550.98 | K24: =G24+H24+I24 -> 26550.98 | L24: =IF(K24<=2000,(0),IF(K24<=4000,(K24*0.15)-300,IF(K24<=7000,(K24*0.2)-500,IF(K24<=10000,(K24*0.25)-850,IF(K24<=14000,(K24*0.3)-1350,IF(K24>14000,(K24*0.35)-2050)))))) -> 7242.843 | M24: =F24*0.07 -> 633.0884 | N24: =F24*0.11 -> 994.8532 | P24: =L24+M24+O24 -> 7875.9314 | Q24: 1500 | R24: =J24-P24+Q24 -> 20175.049
A25: 32 | B25: Erena Gudeta | C25: DSA | D25: Tafo Mission | E25: 30 | F25: 9044.12 | G25: =+F25/30*E25 -> 9044.12 | H25: =3766+8582+8893 -> 21241 | I25: =2788.86 -> 2788.86 | J25: =G25+H25+I25 -> 33073.98 | K25: =G25+H25+I25 -> 33073.98 | L25: =IF(K25<=2000,(0),IF(K25<=4000,(K25*0.15)-300,IF(K25<=7000,(K25*0.2)-500,IF(K25<=10000,(K25*0.25)-850,IF(K25<=14000,(K25*0.3)-1350,IF(K25>14000,(K25*0.35)-2050)))))) -> 9525.893 | M25: =F25*0.07 -> 633.0884 | N25: =F25*0.11 -> 994.8532 | P25: =L25+M25+O25 -> 10158.981 | Q25: 1500 | R25: =J25-P25+Q25 -> 24414.999
A26: 33 | B26: Gebeyaw Aynalem | C26: DSA Coordinator | D26: Tafo | E26: 30 | F26: 9044.12 | G26: =+F26/30*E26 -> 9044.12 | H26: =3929+6686 -> 10615 | I26: =2788.86 -> 2788.86 | J26: =G26+H26+I26 -> 22447.98 | K26: =G26+H26+I26 -> 22447.98 | L26: =IF(K26<=2000,(0),IF(K26<=4000,(K26*0.15)-300,IF(K26<=7000,(K26*0.2)-500,IF(K26<=10000,(K26*0.25)-850,IF(K26<=14000,(K26*0.3)-1350,IF(K26>14000,(K26*0.35)-2050)))))) -> 5806.793 | M26: =F26*0.07 -> 633.0884 | N26: =F26*0.11 -> 994.8532 | P26: =L26+M26+O26 -> 6439.8814 | Q26: 1500 | R26: =J26-P26+Q26 -> 17508.099
A27: 34 | B27: Lakech Eshetu | C27: DSA | D27: Tafo | E27: 30 | F27: 9044.12 | G27: =+F27/30*E27 -> 9044.12 | H27: =1454+2734 -> 4188 | I27: =2788.86 -> 2788.86 | J27: =G27+H27+I27 -> 16020.98 | K27: =G27+H27+I27 -> 16020.98 | L27: =IF(K27<=2000,(0),IF(K27<=4000,(K27*0.15)-300,IF(K27<=7000,(K27*0.2)-500,IF(K27<=10000,(K27*0.25)-850,IF(K27<=14000,(K27*0.3)-1350,IF(K27>14000,(K27*0.35)-2050)))))) -> 3557.343 | M27: =F27*0.07 -> 633.0884 | N27: =F27*0.11 -> 994.8532 | P27: =L27+M27+O27 -> 4190.4314 | Q27: 1500 | R27: =J27-P27+Q27 -> 13330.549
A28: 35 | B28: Mahlet G/wolde | C28: DSA | D28: Hageremariam | E28: 30 | F28: 6164.38 | G28: =+F28/30*E28 -> 6164.38 | H28: =6204+4107 -> 10311 | I28: =1277.63*0 -> 0 | J28: =G28+H28+I28 -> 16475.38 | K28: =G28+H28+I28 -> 16475.38 | L28: =IF(K28<=2000,(0),IF(K28<=4000,(K28*0.15)-300,IF(K28<=7000,(K28*0.2)-500,IF(K28<=10000,(K28*0.25)-850,IF(K28<=14000,(K28*0.3)-1350,IF(K28>14000,(K28*0.35)-2050)))))) -> 3716.383 | M28: =F28*0.07 -> 431.5066 | N28: =F28*0.11 -> 678.0818 | P28: =L28+M28+O28 -> 4147.8896 | R28: =J28-P28+Q28 -> 12327.49
A29: 36 | B29: Arega Jenena | C29: DSA | D29: Sirti | E29: 30 | F29: 6164.38 | G29: =+F29/30*E29 -> 6164.38 | H29: =4673+4673 -> 9346 | I29: 1277.63 | J29: =G29+H29+I29 -> 16788.01 | K29: =G29+H29+I29 -> 16788.01 | L29: =IF(K29<=2000,(0),IF(K29<=4000,(K29*0.15)-300,IF(K29<=7000,(K29*0.2)-500,IF(K29<=10000,(K29*0.25)-850,IF(K29<=14000,(K29*0.3)-1350,IF(K29>14000,(K29*0.35)-2050)))))) -> 3825.8035 | M29: =F29*0.07 -> 431.5066 | N29: =F29*0.11 -> 678.0818 | P29: =L29+M29+O29 -> 4257.3101 | Q29: 1500 | R29: =J29-P29+Q29 -> 14030.7
A30: 37 | B30: Alem Aschenaki | C30: DSA | D30: Mendida | E30: 30 | F30: 6164.38 | G30: =+F30/30*E30 -> 6164.38 | H30: =8143+8142 -> 16285 | I30: 2610.96 | J30: =G30+H30+I30 -> 25060.34 | K30: =G30+H30+I30 -> 25060.34 | L30: =IF(K30<=2000,(0),IF(K30<=4000,(K30*0.15)-300,IF(K30<=7000,(K30*0.2)-500,IF(K30<=10000,(K30*0.25)-850,IF(K30<=14000,(K30*0.3)-1350,IF(K30>14000,(K30*0.35)-2050)))))) -> 6721.119 | M30: =F30*0.07 -> 431.5066 | N30: =F30*0.11 -> 678.0818 | P30: =L30+M30+O30 -> 7152.6256 | Q30: 1500 | R30: =J30-P30+Q30 -> 19407.714
A31: 38 | B31: Aman Nigusu | C31: DSA | D31: Mendida | E31: 30 | F31: 6164.38 | G31: =+F31/30*E31 -> 6164.38 | H31: =25132+12496 -> 37628 | I31: 2610.96 | J31: =G31+H31+I31 -> 46403.34 | K31: =G31+H31+I31 -> 46403.34 | L31: =IF(K31<=2000,(0),IF(K31<=4000,(K31*0.15)-300,IF(K31<=7000,(K31*0.2)-500,IF(K31<=10000,(K31*0.25)-850,IF(K31<=14000,(K31*0.3)-1350,IF(K31>14000,(K31*0.35)-2050)))))) -> 14191.169 | M31: =F31*0.07 -> 431.5066 | N31: =F31*0.11 -> 678.0818 | P31: =L31+M31+O31 -> 14622.676 | Q31: 1500 | R31: =J31-P31+Q31 -> 33280.664
A32: 39 | B32: Fikirte Abiye | C32: DSA | D32: Mendida | E32: 30 | F32: 6164.38 | G32: =+F32/30*E32 -> 6164.38 | H32: =21238+10576 -> 31814 | I32: 2610.96 | J32: =G32+H32+I32 -> 40589.34 | K32: =G32+H32+I32 -> 40589.34 | L32: =IF(K32<=2000,(0),IF(K32<=4000,(K32*0.15)-300,IF(K32<=7000,(K32*0.2)-500,IF(K32<=10000,(K32*0.25)-850,IF(K32<=14000,(K32*0.3)-1350,IF(K32>14000,(K32*0.35)-2050)))))) -> 12156.269 | M32: =F32*0.07 -> 431.5066 | N32: =F32*0.11 -> 678.0818 | P32: =L32+M32+O32 -> 12587.776 | Q32: 1500 | R32: =J32-P32+Q32 -> 29501.564
A33: 40 | B33: Bacha Wondu | C33: DSA | D33: Sendafa | E33: 30 | F33: 4794.52 | G33: =+F33/30*E33 -> 4794.52 | H33: =5958+5946 -> 11904 | I33: =2519.64*0.5 -> 1259.82 | J33: =G33+H33+I33 -> 17958.34 | K33: =G33+H33+I33 -> 17958.34 | L33: =IF(K33<=2000,(0),IF(K33<=4000,(K33*0.15)-300,IF(K33<=7000,(K33*0.2)-500,IF(K33<=10000,(K33*0.25)-850,IF(K33<=14000,(K33*0.3)-1350,IF(K33>14000,(K33*0.35)-2050)))))) -> 4235.419 | M33: =F33*0.07 -> 335.6164 | N33: =F33*0.11 -> 527.3972 | P33: =L33+M33+O33 -> 4571.0354 | Q33: 1500 | R33: =J33-P33+Q33 -> 14887.305
A34: 41 | B34: Birtukan Diriba | C34: DSA | D34: Sendafa Beke | E34: 30 | F34: 9044.12 | G34: =+F34/30*E34 -> 9044.12 | H34: ='Performance Summary'!K6 -> 8560.5 | I34: =2788.86 -> 2788.86 | J34: =G34+H34+I34 -> 20393.48 | K34: =G34+H34+I34 -> 20393.48 | L34: =IF(K34<=2000,(0),IF(K34<=4000,(K34*0.15)-300,IF(K34<=7000,(K34*0.2)-500,IF(K34<=10000,(K34*0.25)-850,IF(K34<=14000,(K34*0.3)-1350,IF(K34>14000,(K34*0.35)-2050)))))) -> 5087.718 | M34: =F34*0.07 -> 633.0884 | N34: =F34*0.11 -> 994.8532 | P34: =L34+M34+O34 -> 5720.8064 | Q34: 1500 | R34: =J34-P34+Q34 -> 16172.674
A35: 42 | B35: Yafet Abiy | C35: DSA | D35: Sendafa | E35: 30 | F35: 9044.12 | G35: =+F35/30*E35 -> 9044.12 | H35: 7064 | I35: =2788.86+7027 -> 9815.86 | J35: =G35+H35+I35 -> 25923.98 | K35: =G35+H35+I35 -> 25923.98 | L35: =IF(K35<=2000,(0),IF(K35<=4000,(K35*0.15)-300,IF(K35<=7000,(K35*0.2)-500,IF(K35<=10000,(K35*0.25)-850,IF(K35<=14000,(K35*0.3)-1350,IF(K35>14000,(K35*0.35)-2050)))))) -> 7023.393 | M35: =F35*0.07 -> 633.0884 | N35: =F35*0.11 -> 994.8532 | P35: =L35+M35+O35 -> 7656.4814 | Q35: 1500 | R35: =J35-P35+Q35 -> 19767.499
A36: 43 | B36: Shiferaw Gebre | C36: DSA | D36: Sheno | E36: 30 | F36: 6164.38 | G36: =+F36/30*E36 -> 6164.38 | H36: =17858+4601 -> 22459 | I36: =2610.96*0.5 -> 1305.48 | J36: =G36+H36+I36 -> 29928.86 | K36: =G36+H36+I36 -> 29928.86 | L36: =IF(K36<=2000,(0),IF(K36<=4000,(K36*0.15)-300,IF(K36<=7000,(K36*0.2)-500,IF(K36<=10000,(K36*0.25)-850,IF(K36<=14000,(K36*0.3)-1350,IF(K36>14000,(K36*0.35)-2050)))))) -> 8425.101 | M36: =F36*0.07 -> 431.5066 | N36: =F36*0.11 -> 678.0818 | P36: =L36+M36+O36 -> 8856.6076 | Q36: 1500 | R36: =J36-P36+Q36 -> 22572.252
A37: 44 | B37: Solomon Hailu | C37: DSA | D37: Sheno | E37: 30 | F37: 6164.38 | G37: =+F37/30*E37 -> 6164.38 | H37: =6931+8893 -> 15824 | I37: 2610.96 | J37: =G37+H37+I37 -> 24599.34 | K37: =G37+H37+I37 -> 24599.34 | L37: =IF(K37<=2000,(0),IF(K37<=4000,(K37*0.15)-300,IF(K37<=7000,(K37*0.2)-500,IF(K37<=10000,(K37*0.25)-850,IF(K37<=14000,(K37*0.3)-1350,IF(K37>14000,(K37*0.35)-2050)))))) -> 6559.769 | M37: =F37*0.07 -> 431.5066 | N37: =F37*0.11 -> 678.0818 | P37: =L37+M37+O37 -> 6991.2756 | Q37: 1500 | R37: =J37-P37+Q37 -> 19108.064
A38: Total | F38: =SUM(F5:F37) -> 248745.24 | G38: =SUM(G5:G37) -> 235481.28 | H38: =SUM(H5:H37) -> 350620.31 | I38: =SUM(I5:I37) -> 72691.53 | J38: =SUM(J5:J37) -> 658793.12 | K38: =SUM(K5:K37) -> 658793.12 | L38: =SUM(L5:L37) -> 166629.91 | M38: =SUM(M5:M37) -> 15714.413 | ... R38: =SUM(R5:R37) -> 517948.79
A40: Prepaired By | G40: Checked By:- | M40: Approved By:-
A41: Name :- _____________________________ | G41: Name :- ______________________________ | M41: Name :- ______________________________
A42: Sign :- ______________________________ | G42: Sign :- ________________________________ | M42: Sign :- ________________________________
A43: Date:- _____________________________ | G43: Date:- _______________________________ | M43: Date:- _______________________________

Sheet EBU Department
A1: LeapFrog Software Technology Africa PLC
A2: Payroll Sheet EBU Staff
A3: For the Month of June 2026/Sene 2018
A4: No. | B4: Name of Employees | C4: Position | D4: Shop Name | E4: Working days | F4: Basic Salary | G4: Monthly Salary | H4: Commiss. /OT | I4: KPI | J4: Gross Salary | K4: Taxable Income | L4: Income Tax | M4: Pension 7% | N4: Pension 11% | O4: Shortage/ Loan | P4: Total Deduction | Q4: Transport & other allowance | R4: Net Pay | S4: sign
A6: 1 | B6: Abuye Behaylu | C6: FTTH teamleader | D6: Ayat49 | E6: 30 | F6: 9044.12 | G6: =+F6/30*E6 -> 9044.12 | I6: =5699.1 -> 5699.1 | J6: =G6+H6+I6 -> 14743.22 | K6: =G6+H6+I6 -> 14743.22 | L6: =IF(K6<=2000,(0),IF(K6<=4000,(K6*0.15)-300,IF(K6<=7000,(K6*0.2)-500,IF(K6<=10000,(K6*0.25)-850,IF(K6<=14000,(K6*0.3)-1350,IF(K6>14000,(K6*0.35)-2050)))))) -> 3110.127 | M6: =F6*0.07 -> 633.0884 | N6: =F6*0.11 -> 994.8532 | P6: =L6+M6+O6 -> 3743.2154 | Q6: =1000+1480 -> 2480 | R6: =J6-P6+Q6 -> 13480.005
A7: 2 | B7: Amanuel Dede | C7: Business Development mgt | D7: Head Office | E7: 30 | F7: 52500 | G7: =+F7/30*E7 -> 52500 | J7: =G7+H7+I7 -> 52500 | K7: =G7+H7+I7 -> 52500 | L7: =IF(K7<=2000,(0),IF(K7<=4000,(K7*0.15)-300,IF(K7<=7000,(K7*0.2)-500,IF(K7<=10000,(K7*0.25)-850,IF(K7<=14000,(K7*0.3)-1350,IF(K7>14000,(K7*0.35)-2050)))))) -> 16325 | M7: =F7*0.07 -> 3675 | N7: =F7*0.11 -> 5775 | O7: 10000 | P7: =L7+M7+O7 -> 30000 | Q7: 2000 | R7: =J7-P7+Q7 -> 24500
A8: 3 | B8: Anbel Haylome | C8: Outdoor Sales | D8: Bole Arabsa | E8: 15 | F8: 7533.33 | G8: =+F8/30*E8 -> 3766.665 | I8: =2680.95*0 -> 0 | J8: =G8+H8+I8 -> 3766.665 | K8: =G8+H8+I8 -> 3766.665 | L8: =IF(K8<=2000,(0),IF(K8<=4000,(K8*0.15)-300,IF(K8<=7000,(K8*0.2)-500,IF(K8<=10000,(K8*0.25)-850,IF(K8<=14000,(K8*0.3)-1350,IF(K8>14000,(K8*0.35)-2050)))))) -> 264.99975 | P8: =L8+M8+O8 -> 264.99975 | Q8: =1000/30*E8 -> 500 | R8: =J8-P8+Q8 -> 4001.6653
A9: 4 | B9: Ashenafi Abdi | C9: FTTH TeamLeader | D9: Abado | E9: 30 | F9: 9044.12 | G9: =+F9/30*E9 -> 9044.12 | I9: 5699.1 | J9: =G9+H9+I9 -> 14743.22 | K9: =G9+H9+I9 -> 14743.22 | L9: =IF(K9<=2000,(0),IF(K9<=4000,(K9*0.15)-300,IF(K9<=7000,(K9*0.2)-500,IF(K9<=10000,(K9*0.25)-850,IF(K9<=14000,(K9*0.3)-1350,IF(K9>14000,(K9*0.35)-2050)))))) -> 3110.127 | M9: =F9*0.07 -> 633.0884 | N9: =F9*0.11 -> 994.8532 | P9: =L9+M9+O9 -> 3743.2154 | Q9: =1000+740 -> 1740 | R9: =J9-P9+Q9 -> 12740.005
A10: 5 | B10: Bereket Alemante | C10: Outdoor Sales | D10: Bole Arabsa | E10: 18 | F10: 7533.33 | G10: =+F10/30*E10 -> 4519.998 | H10: 4914.35 | I10: =2680.95 -> 2680.95 | J10: =G10+H10+I10 -> 12115.298 | K10: =G10+H10+I10 -> 12115.298 | L10: =IF(K10<=2000,(0),IF(K10<=4000,(K10*0.15)-300,IF(K10<=7000,(K10*0.2)-500,IF(K10<=10000,(K10*0.25)-850,IF(K10<=14000,(K10*0.3)-1350,IF(K10>14000,(K10*0.35)-2050)))))) -> 2284.5894 | P10: =L10+M10+O10 -> 2284.5894 | Q10: 2200 | R10: =J10-P10+Q10 -> 12030.709 | S10: =5780-2200 -> 3580 | T10: =12030.71 -> 12030.71
A11: 6 | B11: Bezawit H/Michael | C11: Outdoor Sales | D11: Summit | E11: 18 | F11: 7533.33 | G11: =+F11/30*E11 -> 4519.998 | I11: =2680.95*0 -> 0 | J11: =G11+H11+I11 -> 4519.998 | K11: =G11+H11+I11 -> 4519.998 | L11: =IF(K11<=2000,(0),IF(K11<=4000,(K11*0.15)-300,IF(K11<=7000,(K11*0.2)-500,IF(K11<=10000,(K11*0.25)-850,IF(K11<=14000,(K11*0.3)-1350,IF(K11>14000,(K11*0.35)-2050)))))) -> 403.9996 | P11: =L11+M11+O11 -> 403.9996 | Q11: =1000/30*E11+740 -> 1340 | R11: =J11-P11+Q11 -> 5455.9984
A12: 7 | B12: Biniyam H/Gebriel | C12: FTTH TeamLeader | D12: Bole Arabsa | E12: 30 | F12: 9044.12 | G12: =+F12/30*E12 -> 9044.12 | H12: 5446.15 | I12: =5699.1 -> 5699.1 | J12: =G12+H12+I12 -> 20189.37 | K12: =G12+H12+I12 -> 20189.37 | L12: =IF(K12<=2000,(0),IF(K12<=4000,(K12*0.15)-300,IF(K12<=7000,(K12*0.2)-500,IF(K12<=10000,(K12*0.25)-850,IF(K12<=14000,(K12*0.3)-1350,IF(K12>14000,(K12*0.35)-2050)))))) -> 5016.2795 | P12: =L12+M12+O12 -> 5016.2795 | Q12: 2200 | R12: =J12-P12+Q12 -> 17373.091 | S12: =5740-2200 -> 3540 | T12: 17373.093
A13: 8 | B13: Birtukan Boja | C13: Outdoor Sales | D13: Abado | E13: 30 | F13: 7533.33 | G13: =+F13/30*E13 -> 7533.33 | I13: =2680.95*0 -> 0 | J13: =G13+H13+I13 -> 7533.33 | K13: =G13+H13+I13 -> 7533.33 | L13: =IF(K13<=2000,(0),IF(K13<=4000,(K13*0.15)-300,IF(K13<=7000,(K13*0.2)-500,IF(K13<=10000,(K13*0.25)-850,IF(K13<=14000,(K13*0.3)-1350,IF(K13>14000,(K13*0.35)-2050)))))) -> 1033.3325 | P13: =L13+M13+O13 -> 1033.3325 | Q13: =1000+370 -> 1370 | R13: =J13-P13+Q13 -> 7869.9975
A14: 9 | B14: Birtukan Worku | C14: Outdoor Sales | D14: Bole Arabsa | E14: 30 | F14: 7533.33 | G14: =+F14/30*E14 -> 7533.33 | H14: 5831.87 | I14: =2680.95 -> 2680.95 | J14: =G14+H14+I14 -> 16046.15 | K14: =G14+H14+I14 -> 16046.15 | L14: =IF(K14<=2000,(0),IF(K14<=4000,(K14*0.15)-300,IF(K14<=7000,(K14*0.2)-500,IF(K14<=10000,(K14*0.25)-850,IF(K14<=14000,(K14*0.3)-1350,IF(K14>14000,(K14*0.35)-2050)))))) -> 3566.1525 | P14: =L14+M14+O14 -> 3566.1525 | Q14: 2200 | R14: =J14-P14+Q14 -> 14679.998 | S14: =6180-2200 -> 3980 | T14: 14679.996
A15: 10 | B15: Degeye Derba | C15: Outdoor Sales | D15: Summit | E15: 30 | F15: 7533.33 | G15: =+F15/30*E15 -> 7533.33 | H15: 373.33 | I15: =2680.95*0 -> 0 | J15: =G15+H15+I15 -> 7906.66 | K15: =G15+H15+I15 -> 7906.66 | L15: =IF(K15<=2000,(0),IF(K15<=4000,(K15*0.15)-300,IF(K15<=7000,(K15*0.2)-500,IF(K15<=10000,(K15*0.25)-850,IF(K15<=14000,(K15*0.3)-1350,IF(K15>14000,(K15*0.35)-2050)))))) -> 1126.665 | P15: =L15+M15+O15 -> 1126.665 | Q15: 2200 | R15: =J15-P15+Q15 -> 8979.995 | S15: =2480-2200 -> 280 | T15: 8979.9975
A16: 11 | B16: Derbe Girma | C16: Outdoor Sales | D16: Abado | E16: 30 | F16: 7533.33 | G16: =+F16/30*E16 -> 7533.33 | H16: 866.72 | J16: =G16+H16+I16 -> 8400.05 | K16: =G16+H16+I16 -> 8400.05 | L16: =IF(K16<=2000,(0),IF(K16<=4000,(K16*0.15)-300,IF(K16<=7000,(K16*0.2)-500,IF(K16<=10000,(K16*0.25)-850,IF(K16<=14000,(K16*0.3)-1350,IF(K16>14000,(K16*0.35)-2050)))))) -> 1250.0125 | P16: =L16+M16+O16 -> 1250.0125 | Q16: 2200 | R16: =J16-P16+Q16 -> 9350.0375 | S16: =2850-2200 -> 650 | T16: 9349.9975
A17: 12 | B17: Eyerusalem Gesisa | C17: Outdoor Sales | D17: Summit | E17: 15 | F17: 7534.33 | G17: =+F17/30*E17 -> 3767.165 | I17: =2680.95*0 -> 0 | J17: =G17+H17+I17 -> 3767.165 | K17: =G17+H17+I17 -> 3767.165 | L17: =IF(K17<=2000,(0),IF(K17<=4000,(K17*0.15)-300,IF(K17<=7000,(K17*0.2)-500,IF(K17<=10000,(K17*0.25)-850,IF(K17<=14000,(K17*0.3)-1350,IF(K17>14000,(K17*0.35)-2050)))))) -> 265.07475 | P17: =L17+M17+O17 -> 265.07475 | Q17: =1000 -> 1000 | R17: =J17-P17+Q17 -> 4502.0903
A18: 13 | B18: Eyob Demillie | C18: Outdoor Sales | D18: Bole Arabsa | E18: 30 | F18: 7533.33 | G18: =+F18/30*E18 -> 7533.33 | H18: 1853.33 | J18: =G18+H18+I18 -> 9386.66 | K18: =G18+H18+I18 -> 9386.66 | L18: =IF(K18<=2000,(0),IF(K18<=4000,(K18*0.15)-300,IF(K18<=7000,(K18*0.2)-500,IF(K18<=10000,(K18*0.25)-850,IF(K18<=14000,(K18*0.3)-1350,IF(K18>14000,(K18*0.35)-2050)))))) -> 1496.665 | P18: =L18+M18+O18 -> 1496.665 | Q18: 2200 | R18: =J18-P18+Q18 -> 10089.995 | S18: =3590-2200 -> 1390 | T18: 10089.997
A19: 14 | B19: Firaol tsegayee | C19: Outdoor Sales | D19: Bole Arabsa | E19: 18 | F19: 7533.33 | G19: =+F19/30*E19 -> 4519.998 | I19: =2680.95*0 -> 0 | J19: =G19+H19+I19 -> 4519.998 | K19: =G19+H19+I19 -> 4519.998 | L19: =IF(K19<=2000,(0),IF(K19<=4000,(K19*0.15)-300,IF(K19<=7000,(K19*0.2)-500,IF(K19<=10000,(K19*0.25)-850,IF(K19<=14000,(K19*0.3)-1350,IF(K19>14000,(K19*0.35)-2050)))))) -> 403.9996 | P19: =L19+M19+O19 -> 403.9996 | Q19: =1000+370 -> 1370 | R19: =J19-P19+Q19 -> 5485.9984
A20: 15 | B20: Genet Fisha | C20: Outdoor Sales | D20: Bole Arabsa | E20: 30 | F20: 7533.33 | G20: =+F20/30*E20 -> 7533.33 | H20: 1853.33 | I20: =2680.95*0 -> 0 | J20: =G20+H20+I20 -> 9386.66 | K20: =G20+H20+I20 -> 9386.66 | L20: =IF(K20<=2000,(0),IF(K20<=4000,(K20*0.15)-300,IF(K20<=7000,(K20*0.2)-500,IF(K20<=10000,(K20*0.25)-850,IF(K20<=14000,(K20*0.3)-1350,IF(K20>14000,(K20*0.35)-2050)))))) -> 1496.665 | P20: =L20+M20+O20 -> 1496.665 | Q20: 2200 | R20: =J20-P20+Q20 -> 10089.995 | S20: =3590-2200 -> 1390 | T20: 10089.997
A21: 16 | B21: Hana Belay | C21: Outdoor Sales | D21: Bole Arabsa | E21: 24 | F21: 7533.33 | G21: =+F21/30*E21 -> 6026.664 | H21: 2346.66 | I21: =2680.95*0.5 -> 1340.475 | J21: =G21+H21+I21 -> 9713.799 | K21: =G21+H21+I21 -> 9713.799 | L21: =IF(K21<=2000,(0),IF(K21<=4000,(K21*0.15)-300,IF(K21<=7000,(K21*0.2)-500,IF(K21<=10000,(K21*0.25)-850,IF(K21<=14000,(K21*0.3)-1350,IF(K21>14000,(K21*0.35)-2050)))))) -> 1578.4498 | P21: =L21+M21+O21 -> 1578.4498 | Q21: 2200 | R21: =J21-P21+Q21 -> 10335.349 | S21: =3960-2200 -> 1760 | T21: 10335.354
A22: 17 | B22: Habtamu Assefa | C22: Outdoor Sales | D22: Abado | E22: 30 | F22: 7533.33 | G22: =+F22/30*E22 -> 7533.33 | H22: 1360 | I22: =2680.95*0 -> 0 | J22: =G22+H22+I22 -> 8893.33 | K22: =G22+H22+I22 -> 8893.33 | L22: =IF(K22<=2000,(0),IF(K22<=4000,(K22*0.15)-300,IF(K22<=7000,(K22*0.2)-500,IF(K22<=10000,(K22*0.25)-850,IF(K22<=14000,(K22*0.3)-1350,IF(K22>14000,(K22*0.35)-2050)))))) -> 1373.3325 | P22: =L22+M22+O22 -> 1373.3325 | Q22: 2200 | R22: =J22-P22+Q22 -> 9719.9975 | S22: =3220-2200 -> 1020 | T22: 9719.9975
A23: 18 | B23: Habtamu Tilahun | C23: Outdoor Sales | D23: Abado | E23: 30 | F23: 7533.33 | G23: =+F23/30*E23 -> 7533.33 | H23: 1213.55 | I23: =2680.95*0 -> 0 | J23: =G23+H23+I23 -> 8746.88 | K23: =G23+H23+I23 -> 8746.88 | L23: =IF(K23<=2000,(0),IF(K23<=4000,(K23*0.15)-300,IF(K23<=7000,(K23*0.2)-500,IF(K23<=10000,(K23*0.25)-850,IF(K23<=14000,(K23*0.3)-1350,IF(K23>14000,(K23*0.35)-2050)))))) -> 1336.72 | P23: =L23+M23+O23 -> 1336.72 | Q23: 2200 | R23: =J23-P23+Q23 -> 9610.16 | S23: =3110-2200 -> 910 | T23: 9609.9975
A24: 19 | B24: Haymanot Teferi | C24: Outdoor Sales | D24: Summit | E24: 30 | F24: 7533.33 | G24: =+F24/30*E24 -> 7533.33 | H24: 2805.27 | I24: =2680.95*0.5 -> 1340.475 | J24: =G24+H24+I24 -> 11679.075 | K24: =G24+H24+I24 -> 11679.075 | L24: =IF(K24<=2000,(0),IF(K24<=4000,(K24*0.15)-300,IF(K24<=7000,(K24*0.2)-500,IF(K24<=10000,(K24*0.25)-850,IF(K24<=14000,(K24*0.3)-1350,IF(K24>14000,(K24*0.35)-2050)))))) -> 2153.7225 | P24: =L24+M24+O24 -> 2153.7225 | Q24: 2200 | R24: =J24-P24+Q24 -> 11725.353 | S24: =4220-2200 -> 2020 | T24: 11725.354
A25: 20 | B25: Helen Ashagre | C25: Outdoor Sales | D25: Bole Arabsa | E25: 30 | F25: 7533.33 | G25: =+F25/30*E25 -> 7533.33 | H25: 5093.41 | I25: =2680.95 -> 2680.95 | J25: =G25+H25+I25 -> 15307.69 | K25: =G25+H25+I25 -> 15307.69 | L25: =IF(K25<=2000,(0),IF(K25<=4000,(K25*0.15)-300,IF(K25<=7000,(K25*0.2)-500,IF(K25<=10000,(K25*0.25)-850,IF(K25<=14000,(K25*0.3)-1350,IF(K25>14000,(K25*0.35)-2050)))))) -> 3307.6915 | P25: =L25+M25+O25 -> 3307.6915 | Q25: 2200 | R25: =J25-P25+Q25 -> 14199.998 | S25: =5700-2200 -> 3500 | T25: 14199.996
A26: 21 | B26: Henok Asnake | C26: Outdoor Sales | D26: Bole Arabsa | E26: 30 | F26: 7533.33 | G26: =+F26/30*E26 -> 7533.33 | H26: 2200 | I26: =2680.95*0 -> 0 | J26: =G26+H26+I26 -> 9733.33 | K26: =G26+H26+I26 -> 9733.33 | L26: =IF(K26<=2000,(0),IF(K26<=4000,(K26*0.15)-300,IF(K26<=7000,(K26*0.2)-500,IF(K26<=10000,(K26*0.25)-850,IF(K26<=14000,(K26*0.3)-1350,IF(K26>14000,(K26*0.35)-2050)))))) -> 1583.3325 | P26: =L26+M26+O26 -> 1583.3325 | Q26: 2200 | R26: =J26-P26+Q26 -> 10349.997 | S26: =3850-2200 -> 1650 | T26: 10349.997
A27: 22 | B27: Hermela Chalachew | C27: Outdoor Sales | D27: Bole Arabsa | E27: 30 | F27: 7533.33 | G27: =+F27/30*E27 -> 7533.33 | H27: 7539.56 | I27: =2680.95 -> 2680.95 | J27: =G27+H27+I27 -> 17753.84 | K27: =G27+H27+I27 -> 17753.84 | L27: =IF(K27<=2000,(0),IF(K27<=4000,(K27*0.15)-300,IF(K27<=7000,(K27*0.2)-500,IF(K27<=10000,(K27*0.25)-850,IF(K27<=14000,(K27*0.3)-1350,IF(K27>14000,(K27*0.35)-2050)))))) -> 4163.844 | P27: =L27+M27+O27 -> 4163.844 | Q27: 2200 | R27: =J27-P27+Q27 -> 15789.996 | S27: =7290-2200 -> 5090 | T27: 15789.996
A28: 23 | B28: Hiwot Getu | C28: Outdoor Sales | D28: Summit | E28: 28 | F28: 7533.33 | G28: =+F28/30*E28 -> 7031.108 | I28: =2680.95*0 -> 0 | J28: =G28+H28+I28 -> 7031.108 | K28: =G28+H28+I28 -> 7031.108 | L28: =IF(K28<=2000,(0),IF(K28<=4000,(K28*0.15)-300,IF(K28<=7000,(K28*0.2)-500,IF(K28<=10000,(K28*0.25)-850,IF(K28<=14000,(K28*0.3)-1350,IF(K28>14000,(K28*0.35)-2050)))))) -> 907.777 | P28: =L28+M28+O28 -> 907.777 | Q28: =1000+1110 -> 2110 | R28: =J28-P28+Q28 -> 8233.331
A29: 24 | B29: Kalkidan Tafese | C29: Outdoor Sales | D29: Summit | E29: 30 | F29: 7533.33 | G29: =+F29/30*E29 -> 7533.33 | H29: 3490.98 | I29: =2680.95*0.5 -> 1340.475 | J29: =G29+H29+I29 -> 12364.785 | K29: =G29+H29+I29 -> 12364.785 | L29: =IF(K29<=2000,(0),IF(K29<=4000,(K29*0.15)-300,IF(K29<=7000,(K29*0.2)-500,IF(K29<=10000,(K29*0.25)-850,IF(K29<=14000,(K29*0.3)-1350,IF(K29>14000,(K29*0.35)-2050)))))) -> 2359.4355 | P29: =L29+M29+O29 -> 2359.4355 | Q29: 2200 | R29: =J29-P29+Q29 -> 12205.35 | S29: =4700-2200 -> 2500 | T29: 12205.354
A30: 25 | B30: Mastewal Gullat | C30: Outdoor Sales | D30: Bole Arabsa | E30: 30 | F30: 7533.33 | G30: =+F30/30*E30 -> 7533.33 | I30: =2680.95 -> 2680.95 | J30: =G30+H30+I30 -> 10214.28 | K30: =G30+H30+I30 -> 10214.28 | L30: =IF(K30<=2000,(0),IF(K30<=4000,(K30*0.15)-300,IF(K30<=7000,(K30*0.2)-500,IF(K30<=10000,(K30*0.25)-850,IF(K30<=14000,(K30*0.3)-1350,IF(K30>14000,(K30*0.35)-2050)))))) -> 1714.284 | P30: =L30+M30+O30 -> 1714.284 | Q30: =1000+140 -> 1140 | R30: =J30-P30+Q30 -> 9639.996
A31: 26 | B31: Melat Taye | C31: Outdoor Sales | D31: Abado | E31: 30 | F31: 7533.33 | G31: =+F31/30*E31 -> 7533.33 | H31: 2962.41 | I31: =2680.95*0.5 -> 1340.475 | J31: =G31+H31+I31 -> 11836.215 | K31: =G31+H31+I31 -> 11836.215 | L31: =IF(K31<=2000,(0),IF(K31<=4000,(K31*0.15)-300,IF(K31<=7000,(K31*0.2)-500,IF(K31<=10000,(K31*0.25)-850,IF(K31<=14000,(K31*0.3)-1350,IF(K31>14000,(K31*0.35)-2050)))))) -> 2200.8645 | P31: =L31+M31+O31 -> 2200.8645 | Q31: 2200 | R31: =J31-P31+Q31 -> 11835.351 | S31: =4330-2200 -> 2130 | T31: 11835.354
A32: 28 | B32: Mistire Amezenechi | C32: Outdoor Sales | D32: Summit | E32: 18 | F32: 7533.33 | G32: =+F32/30*E32 -> 4519.998 | I32: =2680.95*0 -> 0 | J32: =G32+H32+I32 -> 4519.998 | K32: =G32+H32+I32 -> 4519.998 | L32: =IF(K32<=2000,(0),IF(K32<=4000,(K32*0.15)-300,IF(K32<=7000,(K32*0.2)-500,IF(K32<=10000,(K32*0.25)-850,IF(K32<=14000,(K32*0.3)-1350,IF(K32>14000,(K32*0.35)-2050)))))) -> 403.9996 | P32: =L32+M32+O32 -> 403.9996 | Q32: =1000+370 -> 1370 | R32: =J32-P32+Q32 -> 5485.9984
A33: 29 | B33: Mihiret Sisay | C33: Outdoor Sales | D33: Abado | E33: 30 | F33: 7533.33 | G33: =+F33/30*E33 -> 7533.33 | I33: =2680.95*0 -> 0 | J33: =G33+H33+I33 -> 7533.33 | K33: =G33+H33+I33 -> 7533.33 | L33: =IF(K33<=2000,(0),IF(K33<=4000,(K33*0.15)-300,IF(K33<=7000,(K33*0.2)-500,IF(K33<=10000,(K33*0.25)-850,IF(K33<=14000,(K33*0.3)-1350,IF(K33>14000,(K33*0.35)-2050)))))) -> 1033.3325 | P33: =L33+M33+O33 -> 1033.3325 | Q33: =1000+740 -> 1740 | R33: =J33-P33+Q33 -> 8239.9975
A34: 31 | B34: Rehima Senbti | C34: Outdoor Sales | D34: Summit | E34: 18 | F34: 7532.33 | G34: =+F34/30*E34 -> 4519.398 | I34: =2680.95*0 -> 0 | J34: =G34+H34+I34 -> 4519.398 | K34: =G34+H34+I34 -> 4519.398 | L34: =IF(K34<=2000,(0),IF(K34<=4000,(K34*0.15)-300,IF(K34<=7000,(K34*0.2)-500,IF(K34<=10000,(K34*0.25)-850,IF(K34<=14000,(K34*0.3)-1350,IF(K34>14000,(K34*0.35)-2050)))))) -> 403.8796 | P34: =L34+M34+O34 -> 403.8796 | Q34: =1000+370 -> 1370 | R34: =J34-P34+Q34 -> 5485.5184
A35: 32 | B35: Samrawit Chale | C35: Outdoor Sales | D35: Bole Arabsa | E35: 23 | F35: 7532.33 | G35: =+F35/30*E35 -> 5774.7863 | I35: =2680.95*0 -> 0 | J35: =G35+H35+I35 -> 5774.7863 | K35: =G35+H35+I35 -> 5774.7863 | L35: =IF(K35<=2000,(0),IF(K35<=4000,(K35*0.15)-300,IF(K35<=7000,(K35*0.2)-500,IF(K35<=10000,(K35*0.25)-850,IF(K35<=14000,(K35*0.3)-1350,IF(K35>14000,(K35*0.35)-2050)))))) -> 654.95727 | P35: =L35+M35+O35 -> 654.95727 | Q35: =1000/30*E35+1110 -> 1876.6667 | R35: =J35-P35+Q35 -> 6996.4957
A36: 34 | B36: Sena Debebe | C36: Outdoor Sales | D36: Summit | E36: 18 | F36: 7533.33 | G36: =+F36/30*E36 -> 4519.998 | I36: =2680.95*0 -> 0 | J36: =G36+H36+I36 -> 4519.998 | K36: =G36+H36+I36 -> 4519.998 | L36: =IF(K36<=2000,(0),IF(K36<=4000,(K36*0.15)-300,IF(K36<=7000,(K36*0.2)-500,IF(K36<=10000,(K36*0.25)-850,IF(K36<=14000,(K36*0.3)-1350,IF(K36>14000,(K36*0.35)-2050)))))) -> 403.9996 | P36: =L36+M36+O36 -> 403.9996 | Q36: =1000+1370 -> 2370 | R36: =J36-P36+Q36 -> 6485.9984
A37: 35 | B37: Solomon Wondesen | C37: Outdoor Sales | D37: Summit | E37: 43 | F37: 7533.33 | G37: =+F37/30*E37 -> 10797.773 | H37: 1019.04 | I37: =2680.95*0 -> 0 | J37: =G37+H37+I37 -> 11816.813 | K37: =G37+H37+I37 -> 11816.813 | L37: =IF(K37<=2000,(0),IF(K37<=4000,(K37*0.15)-300,IF(K37<=7000,(K37*0.2)-500,IF(K37<=10000,(K37*0.25)-850,IF(K37<=14000,(K37*0.3)-1350,IF(K37>14000,(K37*0.35)-2050)))))) -> 2195.0439 | P37: =L37+M37+O37 -> 2195.0439 | Q37: 2200 | R37: =J37-P37+Q37 -> 11821.769 | S37: =2913.33-2200 -> 713.33 | T37: 11821.774
A38: 36 | B38: Temesgen Asefa | C38: Outdoor Sales | D38: Abado | E38: 30 | F38: 7533.33 | G38: =+F38/30*E38 -> 7533.33 | H38: 3490.98 | I38: =2680.95*0.5 -> 1340.475 | J38: =G38+H38+I38 -> 12364.785 | K38: =G38+H38+I38 -> 12364.785 | L38: =IF(K38<=2000,(0),IF(K38<=4000,(K38*0.15)-300,IF(K38<=7000,(K38*0.2)-500,IF(K38<=10000,(K38*0.25)-850,IF(K38<=14000,(K38*0.3)-1350,IF(K38>14000,(K38*0.35)-2050)))))) -> 2359.4355 | P38: =L38+M38+O38 -> 2359.4355 | Q38: 2200 | R38: =J38-P38+Q38 -> 12205.35 | S38: =4700-2200 -> 2500 | T38: 12205.354
A39: 37 | B39: Temesgen Gubena | C39: Outdoor Sales | D39: Summit | E39: 30 | F39: 7533.33 | G39: =+F39/30*E39 -> 7533.33 | H39: 2962.41 | I39: =2680.95*0.5 -> 1340.475 | J39: =G39+H39+I39 -> 11836.215 | K39: =G39+H39+I39 -> 11836.215 | L39: =IF(K39<=2000,(0),IF(K39<=4000,(K39*0.15)-300,IF(K39<=7000,(K39*0.2)-500,IF(K39<=10000,(K39*0.25)-850,IF(K39<=14000,(K39*0.3)-1350,IF(K39>14000,(K39*0.35)-2050)))))) -> 2200.8645 | P39: =L39+M39+O39 -> 2200.8645 | Q39: 2200 | R39: =J39-P39+Q39 -> 11835.351 | S39: =4330-2200 -> 2130 | T39: 11835.354
A40: 38 | B40: Tigist Admasu | C40: Outdoor Sales | D40: Abado | E40: 30 | F40: 7533.33 | G40: =+F40/30*E40 -> 7533.33 | H40: 4019.55 | I40: =2680.95*0.5 -> 1340.475 | J40: =G40+H40+I40 -> 12893.355 | K40: =G40+H40+I40 -> 12893.355 | L40: =IF(K40<=2000,(0),IF(K40<=4000,(K40*0.15)-300,IF(K40<=7000,(K40*0.2)-500,IF(K40<=10000,(K40*0.25)-850,IF(K40<=14000,(K40*0.3)-1350,IF(K40>14000,(K40*0.35)-2050)))))) -> 2518.0065 | P40: =L40+M40+O40 -> 2518.0065 | Q40: 2200 | R40: =J40-P40+Q40 -> 12575.349 | S40: =5070-2200 -> 2870 | T40: 12575.354
A41: 40 | B41: Tsion Fikeru | C41: Outdoor Sales | D41: Bole Arabsa | E41: 30 | F41: 7533.33 | G41: =+F41/30*E41 -> 7533.33 | H41: 11524.18 | I41: =2680.95 -> 2680.95 | J41: =G41+H41+I41 -> 21738.46 | K41: =G41+H41+I41 -> 21738.46 | L41: =IF(K41<=2000,(0),IF(K41<=4000,(K41*0.15)-300,IF(K41<=7000,(K41*0.2)-500,IF(K41<=10000,(K41*0.25)-850,IF(K41<=14000,(K41*0.3)-1350,IF(K41>14000,(K41*0.35)-2050)))))) -> 5558.461 | P41: =L41+M41+O41 -> 5558.461 | Q41: 2200 | R41: =J41-P41+Q41 -> 18379.999 | S41: =9880-2200 -> 7680 | T41: 18379.996
A42: 41 | B42: Wassihun Getu | C42: FTTH Mgr | D42: BoleArabsa | E42: 30 | F42: 39568.97 | G42: =+F42/30*E42 -> 39568.97 | H42: 9030 | J42: =G42+H42+I42 -> 48598.97 | K42: =G42+H42+I42 -> 48598.97 | L42: =IF(K42<=2000,(0),IF(K42<=4000,(K42*0.15)-300,IF(K42<=7000,(K42*0.2)-500,IF(K42<=10000,(K42*0.25)-850,IF(K42<=14000,(K42*0.3)-1350,IF(K42>14000,(K42*0.35)-2050)))))) -> 14959.64 | M42: =F42*0.07 -> 2769.8279 | N42: =F42*0.11 -> 4352.5867 | P42: =L42+M42+O42 -> 17729.467 | Q42: 2000 | R42: =J42-P42+Q42 -> 32869.503
A43: 42 | B43: Yeabsira Abebe | C43: Outdoor Sales | D43: Abado | E43: 31 | F43: 7533.33 | G43: =+F43/30*E43 -> 7784.441 | I43: =2680.95*0 -> 0 | J43: =G43+H43+I43 -> 7784.441 | K43: =G43+H43+I43 -> 7784.441 | L43: =IF(K43<=2000,(0),IF(K43<=4000,(K43*0.15)-300,IF(K43<=7000,(K43*0.2)-500,IF(K43<=10000,(K43*0.25)-850,IF(K43<=14000,(K43*0.3)-1350,IF(K43>14000,(K43*0.35)-2050)))))) -> 1096.1102 | P43: =L43+M43+O43 -> 1096.1102 | Q43: =1000+1110 -> 2110 | R43: =J43-P43+Q43 -> 8798.3308
A44: 43 | B44: Yewubdar Kefyalew | C44: Outdoor Sales | D44: Bole Arabsa | E44: 30 | F44: 7533.33 | G44: =+F44/30*E44 -> 7533.33 | H44: 2962.41 | I44: =2680.95*0.5 -> 1340.475 | J44: =G44+H44+I44 -> 11836.215 | K44: =G44+H44+I44 -> 11836.215 | L44: =IF(K44<=2000,(0),IF(K44<=4000,(K44*0.15)-300,IF(K44<=7000,(K44*0.2)-500,IF(K44<=10000,(K44*0.25)-850,IF(K44<=14000,(K44*0.3)-1350,IF(K44>14000,(K44*0.35)-2050)))))) -> 2200.8645 | P44: =L44+M44+O44 -> 2200.8645 | Q44: 2200 | R44: =J44-P44+Q44 -> 11835.351 | S44: =4330-2200 -> 2130 | T44: 11835.354
A45: 44 | B45: Yosef Chalachew | C45: Outdoor Sales | D45: BoleArabsa | E45: 30 | F45: 7533.33 | G45: =+F45/30*E45 -> 7533.33 | H45: 1706.67 | I45: =2680.95*0 -> 0 | J45: =G45+H45+I45 -> 9240 | K45: =G45+H45+I45 -> 9240 | L45: =IF(K45<=2000,(0),IF(K45<=4000,(K45*0.15)-300,IF(K45<=7000,(K45*0.2)-500,IF(K45<=10000,(K45*0.25)-850,IF(K45<=14000,(K45*0.3)-1350,IF(K45>14000,(K45*0.35)-2050)))))) -> 1460 | P45: =L45+M45+O45 -> 1460 | Q45: 2200 | R45: =J45-P45+Q45 -> 9980 | S45: =3480-2200 -> 1280 | T45: 9979.9975
B46: Total | F46: =SUM(F6:F45) -> 382866.88 | G46: =SUM(G6:G45) -> 357002.58 | H46: =SUM(H6:H45) -> 86866.16 | I46: =SUM(I6:I45) -> 43906.8 | J46: =SUM(J6:J45) -> 487775.54 | K46: =SUM(K6:K45) -> 487775.54 | L46: =SUM(L6:L45) -> 101281.74 | M46: =SUM(M6:M45) -> 7711.0047 | ... R46: =SUM(R6:R45) -> 447269.47
A49: Prepaired By | G49: Checked By:- | M49: Approved By:-
A50: Name :- _____________________________ | G50: Name :- ______________________________ | M50: Name :- ______________________________
A51: Sign :- ______________________________ | G51: Sign :- ________________________________ | M51: Sign :- ________________________________
A52: Date:- _____________________________ | G52: Date:- _______________________________ | M52: Date:- _______________________________

Sheet Aleletu
A1: LeapFrog Software Technology Africa PLC
A2: Payroll Sheet Aleltu shop
A3: For the Month of Sene 2018
A4: No. | B4: Name of Employees | C4: Position | D4: Work place | E4: Working days | F4: Basic Salary | G4: Monthly Salary | H4: Commiss. /OT | I4: KPI | J4: Gross Salary | K4: Taxable Income | L4: Income Tax | M4: Pension 7% | N4: Pension 11% | O4: Shortage/ Loan | P4: Total Deduction | Q4: Transport & other allowance | R4: Net Pay | S4: sign
A5: 1 | B5: Fana Abebe | C5: DSP | D5: Aleltu | E5: 30 | F5: 3176.47 | G5: =+F5/30*E5 -> 3176.47 | J5: =G5+H5+I5 -> 3176.47 | K5: =G5+H5+I5 -> 3176.47 | L5: =IF(K5<=2000,(0),IF(K5<=4000,(K5*0.15)-300,IF(K5<=7000,(K5*0.2)-500,IF(K5<=10000,(K5*0.25)-850,IF(K5<=14000,(K5*0.3)-1350,IF(K5>14000,(K5*0.35)-2050)))))) -> 176.4705 | P5: =L5+M5+O5 -> 176.4705 | R5: =J5-P5+Q5 -> 2999.9995
A6: 2 | B6: Getenet Worku | C6: Shop SV | D6: Aleltu | E6: 30 | F6: 9044.12 | G6: =+F6/30*E6 -> 9044.12 | H6: 16 | I6: =2788.86/30*E6 -> 2788.86 | J6: =G6+H6+I6 -> 11848.98 | K6: =G6+H6+I6 -> 11848.98 | L6: =IF(K6<=2000,(0),IF(K6<=4000,(K6*0.15)-300,IF(K6<=7000,(K6*0.2)-500,IF(K6<=10000,(K6*0.25)-850,IF(K6<=14000,(K6*0.3)-1350,IF(K6>14000,(K6*0.35)-2050)))))) -> 2204.694 | M6: =F6*0.07 -> 633.0884 | N6: =F6*0.11 -> 994.8532 | P6: =L6+M6+O6 -> 2837.7824 | Q6: 1000 | R6: =J6-P6+Q6 -> 10011.198
A7: 3 | B7: Hana Bulo Bekele | C7: DSP | D7: Aleltu | E7: 30 | F7: 7573.53 | G7: =+F7/30*E7 -> 7573.53 | I7: =2683.83/30*E7 -> 2683.83 | J7: =G7+H7+I7 -> 10257.36 | K7: =G7+H7+I7 -> 10257.36 | L7: =IF(K7<=2000,(0),IF(K7<=4000,(K7*0.15)-300,IF(K7<=7000,(K7*0.2)-500,IF(K7<=10000,(K7*0.25)-850,IF(K7<=14000,(K7*0.3)-1350,IF(K7>14000,(K7*0.35)-2050)))))) -> 1727.208 | M7: =F7*0.07 -> 530.1471 | N7: =F7*0.11 -> 833.0883 | P7: =L7+M7+O7 -> 2257.3551 | R7: =J7-P7+Q7 -> 8000.0049
A8: Total | F8: =SUM(F5:F7) -> 19794.12 | G8: =SUM(G5:G7) -> 19794.12 | H8: =SUM(H5:H7) -> 16 | I8: =SUM(I5:I7) -> 5472.69 | J8: =SUM(J5:J7) -> 25282.81 | K8: =SUM(K5:K7) -> 25282.81 | L8: =SUM(L5:L7) -> 4108.3725 | M8: =SUM(M5:M7) -> 1163.2355 | ... R8: =SUM(R5:R7) -> 21011.202
A10: Prepaired By | G10: Checked By:- | M10: Approved By:-
A11: Name :- _____________________________ | G11: Name :- ______________________________ | M11: Name :- ______________________________
A12: Sign :- ______________________________ | G12: Sign :- ________________________________ | M12: Sign :- ________________________________
A13: Date:- _____________________________ | G13: Date:- _______________________________ | M13: Date:- _______________________________

Sheet Chacha
A1: LeapFrog Software Technology Africa PLC
A2: Payroll Sheet Chacha shop
A3: For the Month of Sene 2018
A5: No. | B5: Name of Employees | C5: Position | D5: Work place | E5: Working days | F5: Basic Salary | G5: Monthly Salary | H5: Commiss. /OT | I5: KPI | J5: Gross Salary | K5: Taxable Income | L5: Income Tax | M5: Pension 7% | N5: Pension 11% | O5: Shortage/ Loan | P5: Total Deduction | Q5: Transport & other allowance | R5: Net Pay | S5: sign
A6: 1 | B6: Fanose Tesfaye | C6: DSP | D6: Chacha | E6: 30 | F6: 7573.53 | G6: =+F6/30*E6 -> 7573.53 | I6: =2683.83/30*E6 -> 2683.83 | J6: =G6+H6+I6 -> 10257.36 | K6: =G6+H6+I6 -> 10257.36 | L6: =IF(K6<=2000,(0),IF(K6<=4000,(K6*0.15)-300,IF(K6<=7000,(K6*0.2)-500,IF(K6<=10000,(K6*0.25)-850,IF(K6<=14000,(K6*0.3)-1350,IF(K6>14000,(K6*0.35)-2050)))))) -> 1727.208 | M6: =F6*0.07 -> 530.1471 | N6: =F6*0.11 -> 833.0883 | P6: =L6+M6+O6 -> 2257.3551 | Q6: =1000/30*E6 -> 1000 | R6: =J6-P6+Q6 -> 9000.0049
A7: 2 | B7: Mikiyas Tadesse | C7: SM | D7: Chacha | E7: 30 | F7: 17155.18 | G7: =+F7/30*E7 -> 17155.18 | I7: 3076.92 | J7: =G7+H7+I7 -> 20232.1 | K7: =G7+H7+I7 -> 20232.1 | L7: =IF(K7<=2000,(0),IF(K7<=4000,(K7*0.15)-300,IF(K7<=7000,(K7*0.2)-500,IF(K7<=10000,(K7*0.25)-850,IF(K7<=14000,(K7*0.3)-1350,IF(K7>14000,(K7*0.35)-2050)))))) -> 5031.235 | M7: =F7*0.07 -> 1200.8626 | N7: =F7*0.11 -> 1887.0698 | P7: =L7+M7+O7 -> 6232.0976 | R7: =J7-P7+Q7 -> 14000.002
A8: 3 | B8: Sosna Tesfaye | C8: Cleaner | D8: Chacha | E8: 30 | F8: 1612.9 | G8: =+F8/30*E8 -> 1612.9 | J8: =G8+H8+I8 -> 1612.9 | K8: =G8+H8+I8 -> 1612.9 | L8: =IF(K8<=2000,(0),IF(K8<=4000,(K8*0.15)-300,IF(K8<=7000,(K8*0.2)-500,IF(K8<=10000,(K8*0.25)-850,IF(K8<=14000,(K8*0.3)-1350,IF(K8>14000,(K8*0.35)-2050)))))) -> 0 | P8: =L8+M8+O8 -> 0 | R8: =J8-P8+Q8 -> 1612.9
A9: Total | F9: =SUM(F6:F8) -> 26341.61 | G9: =SUM(G6:G8) -> 26341.61 | H9: =SUM(H6:H8) -> 0 | I9: =SUM(I6:I8) -> 5760.75 | J9: =SUM(J6:J8) -> 32102.36 | K9: =SUM(K6:K8) -> 32102.36 | L9: =SUM(L6:L8) -> 6758.443 | M9: =SUM(M6:M8) -> 1731.0097 | ... R9: =SUM(R6:R8) -> 24612.907
A11: Prepaired By | G11: Checked By:- | M11: Approved By:-
A12: Name :- _____________________________ | G12: Name :- ______________________________ | M12: Name :- ______________________________
A13: Sign :- ______________________________ | G13: Sign :- ________________________________ | M13: Sign :- ________________________________
A14: Date:- _____________________________ | G14: Date:- _______________________________ | M14: Date:- _______________________________

Sheet Legetafo
A1: LeapFrog Software Technology Africa PLC
A2: Payroll Sheet Lege-Tafo
A3: For the Month of Sene 2018
A5: No. | B5: Name of Employees | C5: Position | D5: Work place | E5: Working days | F5: Basic Salary | G5: Monthly Salary | H5: Commiss. /OT | I5: KPI | J5: Gross Salary | K5: Taxable Income | L5: Income Tax | M5: Pension 7% | N5: Pension 11% | O5: Shortage/ Loan | P5: Total Deduction | Q5: Transport & other allowance | R5: Net Pay | S5: sign
A6: 1 | B6: Addisu Asefa | C6: Ba Coordinator | D6: Tafo | E6: 50 | F6: 4794.52 | G6: =+F6/30*E6 -> 7990.8667 | I6: =2654.34*0 -> 0 | J6: =G6+H6+I6 -> 7990.8667 | K6: =G6+H6+I6 -> 7990.8667 | L6: =IF(K6<=2000,(0),IF(K6<=4000,(K6*0.15)-300,IF(K6<=7000,(K6*0.2)-500,IF(K6<=10000,(K6*0.25)-850,IF(K6<=14000,(K6*0.3)-1350,IF(K6>14000,(K6*0.35)-2050)))))) -> 1147.7167 | M6: =F6*0.07 -> 335.6164 | N6: =F6*0.11 -> 527.3972 | P6: =L6+M6+O6 -> 1483.3331 | Q6: =1000/30*E6 -> 1666.6667 | R6: =J6-P6+Q6 -> 8174.2003
A7: 2 | B7: Feyisa Ayana | C7: SM | D7: Tafo | E7: 30 | F7: 21724.14 | G7: =+F7/30*E7 -> 21724.14 | I7: =1846.15*0 -> 0 | J7: =G7+H7+I7 -> 21724.14 | K7: =G7+H7+I7 -> 21724.14 | L7: =IF(K7<=2000,(0),IF(K7<=4000,(K7*0.15)-300,IF(K7<=7000,(K7*0.2)-500,IF(K7<=10000,(K7*0.25)-850,IF(K7<=14000,(K7*0.3)-1350,IF(K7>14000,(K7*0.35)-2050)))))) -> 5553.449 | M7: =F7*0.07 -> 1520.6898 | N7: =F7*0.11 -> 2389.6554 | P7: =L7+M7+O7 -> 7074.1388 | Q7: 2000 | R7: =J7-P7+Q7 -> 16650.001
A8: 3 | B8: Gudina Gudeta | C8: Security | D8: Tafo | E8: 30 | F8: 4794.52 | G8: =+F8/30*E8 -> 4794.52 | J8: =G8+H8+I8 -> 4794.52 | K8: =G8+H8+I8 -> 4794.52 | L8: =IF(K8<=2000,(0),IF(K8<=4000,(K8*0.15)-300,IF(K8<=7000,(K8*0.2)-500,IF(K8<=10000,(K8*0.25)-850,IF(K8<=14000,(K8*0.3)-1350,IF(K8>14000,(K8*0.35)-2050)))))) -> 458.904 | M8: =F8*0.07 -> 335.6164 | N8: =F8*0.11 -> 527.3972 | P8: =L8+M8+O8 -> 794.5204 | R8: =J8-P8+Q8 -> 3999.9996
A9: 4 | B9: Hadiya Abdi | C9: DSP | D9: Tafo Mission | E9: 30 | F9: 8007.94 | G9: =+F9/30*E9 -> 8007.94 | I9: =2857.14 -> 2857.14 | J9: =G9+H9+I9 -> 10865.08 | K9: =G9+H9+I9 -> 10865.08 | L9: =IF(K9<=2000,(0),IF(K9<=4000,(K9*0.15)-300,IF(K9<=7000,(K9*0.2)-500,IF(K9<=10000,(K9*0.25)-850,IF(K9<=14000,(K9*0.3)-1350,IF(K9>14000,(K9*0.35)-2050)))))) -> 1909.524 | M9: =F9*0.07 -> 560.5558 | N9: =F9*0.11 -> 880.8734 | P9: =L9+M9+O9 -> 2470.0798 | Q9: 1000 | R9: =J9-P9+Q9 -> 9395.0002
A10: 5 | B10: Haimanot Alemu | C10: S.Accountant | D10: Tafo | E10: 30 | F10: 9729.07 | G10: =+F10/30*E10 -> 9729.07 | I10: =2857.14 -> 2857.14 | J10: =G10+H10+I10 -> 12586.21 | K10: =G10+H10+I10 -> 12586.21 | L10: =IF(K10<=2000,(0),IF(K10<=4000,(K10*0.15)-300,IF(K10<=7000,(K10*0.2)-500,IF(K10<=10000,(K10*0.25)-850,IF(K10<=14000,(K10*0.3)-1350,IF(K10>14000,(K10*0.35)-2050)))))) -> 2425.863 | M10: =F10*0.07 -> 681.0349 | N10: =F10*0.11 -> 1070.1977 | P10: =L10+M10+O10 -> 3106.8979 | Q10: 1000 | R10: =J10-P10+Q10 -> 10479.312
A11: 6 | B11: Meti Abdisa | C11: DSP | D11: Tafo Mission | E11: 10 | F11: 8007.94 | G11: =+F11/30*E11 -> 2669.3133 | I11: =2857.14 -> 2857.14 | J11: =G11+H11+I11 -> 5526.4533 | K11: =G11+H11+I11 -> 5526.4533 | L11: =IF(K11<=2000,(0),IF(K11<=4000,(K11*0.15)-300,IF(K11<=7000,(K11*0.2)-500,IF(K11<=10000,(K11*0.25)-850,IF(K11<=14000,(K11*0.3)-1350,IF(K11>14000,(K11*0.35)-2050)))))) -> 605.29067 | M11: =F11*0.07 -> 560.5558 | N11: =F11*0.11 -> 880.8734 | P11: =L11+M11+O11 -> 1165.8465 | Q11: 1000 | R11: =J11-P11+Q11 -> 5360.6069
A12: 7 | B12: Rahel G/Selam | C12: Device SV | D12: Tafo | E12: 30 | F12: 11206.9 | G12: =+F12/30*E12 -> 11206.9 | I12: =3076.92*0.5 -> 1538.46 | J12: =G12+H12+I12 -> 12745.36 | K12: =G12+H12+I12 -> 12745.36 | L12: =IF(K12<=2000,(0),IF(K12<=4000,(K12*0.15)-300,IF(K12<=7000,(K12*0.2)-500,IF(K12<=10000,(K12*0.25)-850,IF(K12<=14000,(K12*0.3)-1350,IF(K12>14000,(K12*0.35)-2050)))))) -> 2473.608 | M12: =F12*0.07 -> 784.483 | N12: =F12*0.11 -> 1232.759 | P12: =L12+M12+O12 -> 3258.091 | Q12: =1000+370 -> 1370 | R12: =J12-P12+Q12 -> 10857.269
A13: 8 | B13: Zeyiba Adem | C13: Cleaner | D13: Tafo | E13: 30 | F13: 2179.49 | G13: =+F13/30*E13 -> 2179.49 | J13: =G13+H13+I13 -> 2179.49 | K13: =G13+H13+I13 -> 2179.49 | L13: =IF(K13<=2000,(0),IF(K13<=4000,(K13*0.15)-300,IF(K13<=7000,(K13*0.2)-500,IF(K13<=10000,(K13*0.25)-850,IF(K13<=14000,(K13*0.3)-1350,IF(K13>14000,(K13*0.35)-2050)))))) -> 26.9235 | M13: =F13*0.07 -> 152.5643 | N13: =F13*0.11 -> 239.7439 | P13: =L13+M13+O13 -> 179.4878 | Q13: 500 | R13: =J13-P13+Q13 -> 2500.0022
A14: Total | F14: =SUM(F6:F13) -> 70444.52 | G14: =SUM(G6:G13) -> 68302.24 | H14: =SUM(H6:H13) -> 0 | I14: =SUM(I6:I13) -> 10109.88 | J14: =SUM(J6:J13) -> 78412.12 | K14: =SUM(K6:K13) -> 78412.12 | L14: =SUM(L6:L13) -> 14601.279 | M14: =SUM(M6:M13) -> 4931.1164 | ... R14: =SUM(R6:R13) -> 67416.391
A17: Prepaired By | G17: Checked By:- | M17: Approved By:-
A18: Name :- _____________________________ | G18: Name :- ______________________________ | M18: Name :- ______________________________
A19: Sign :- ______________________________ | G19: Sign :- ________________________________ | M19: Sign :- ________________________________
A20: Date:- _____________________________ | G20: Date:- _______________________________ | M20: Date:- _______________________________

Sheet Hmariam
A1: LeapFrog Software Technology Africa PLC
A2: Payroll Sheet Hageremariam shop
A3: For the Month of Sene 2018
A5: No. | B5: Name of Employees | C5: Position | D5: Work place | E5: Working days | F5: Basic Salary | G5: Monthly Salary | H5: Commiss. /OT | I5: KPI | J5: Gross Salary | K5: Taxable Income | L5: Income Tax | M5: Pension 7% | N5: Pension 11% | O5: Shortage/ Loan | P5: Total Deduction | Q5: Transport & other allowance | R5: Net Pay | S5: sign
A6: 1 | B6: Ashenafi Deres | C6: SM | D6: Hageremariam | E6: 12 | F6: 6164.38 | G6: =+F6/30*E6 -> 2465.752 | I6: 3952.06 | J6: =G6+H6+I6 -> 6417.812 | K6: =G6+H6+I6 -> 6417.812 | L6: =IF(K6<=2000,(0),IF(K6<=4000,(K6*0.15)-300,IF(K6<=7000,(K6*0.2)-500,IF(K6<=10000,(K6*0.25)-850,IF(K6<=14000,(K6*0.3)-1350,IF(K6>14000,(K6*0.35)-2050)))))) -> 783.5624 | M6: =F6*0.07 -> 431.5066 | N6: =G6*0.11 -> 271.23272 | P6: =L6+M6+O6 -> 1215.069 | Q6: 1000 | R6: =J6-P6+Q6 -> 6202.743
A7: 2 | B7: Moges Neguse | C7: SM | D7: Hageremariam | E7: 18 | F7: 6164.38 | G7: =+F7/30*E7 -> 3698.628 | I7: 3952.06 | J7: =G7+H7+I7 -> 7650.688 | K7: =G7+H7+I7 -> 7650.688 | L7: =IF(K7<=2000,(0),IF(K7<=4000,(K7*0.15)-300,IF(K7<=7000,(K7*0.2)-500,IF(K7<=10000,(K7*0.25)-850,IF(K7<=14000,(K7*0.3)-1350,IF(K7>14000,(K7*0.35)-2050)))))) -> 1062.672 | M7: =F7*0.07 -> 431.5066 | N7: =G7*0.11 -> 406.84908 | P7: =L7+M7+O7 -> 1494.1786 | Q7: 1000 | R7: =J7-P7+Q7 -> 7156.5094
A8: Total | F8: =SUM(F6:F7) -> 12328.76 | G8: =SUM(G6:G7) -> 6164.38 | H8: =SUM(H6:H7) -> 0 | I8: =SUM(I6:I7) -> 7904.12 | J8: =SUM(J6:J7) -> 14068.5 | K8: =SUM(K6:K7) -> 14068.5 | L8: =SUM(L6:L7) -> 1846.2344 | M8: =SUM(M6:M7) -> 863.0132 | ... R8: =SUM(R6:R7) -> 13359.252
A11: Prepaired By | G11: Checked By:- | M11: Approved By:-
A12: Name :- _____________________________ | G12: Name :- ______________________________ | M12: Name :- ______________________________
A13: Sign :- ______________________________ | G13: Sign :- ________________________________ | M13: Sign :- ________________________________
A14: Date:- _____________________________ | G14: Date:- _______________________________ | M14: Date:- _______________________________

Sheet Sirti
A1: LeapFrog Software Technology Africa PLC
A2: Payroll Sheet Sirti shop
A3: For the Month of Sene 2018
A5: No. | B5: Name of Employees | C5: Position | D5: Work place | E5: Working days | F5: Basic Salary | G5: Monthly Salary | H5: Commiss. /OT | I5: KPI | J5: Gross Salary | K5: Taxable Income | L5: Income Tax | M5: Pension 7% | N5: Pension 11% | O5: Shortage/ Loan | P5: Total Deduction | Q5: Transport & other allowance | R5: Net Pay | S5: sign
A6: 1 | B6: Lishe Baza Assefa | C6: SM | D6: Sirti | E6: 30 | F6: 9044.12 | G6: =+F6/30*E6 -> 9044.12 | I6: 2788.86 | J6: =G6+H6+I6 -> 11832.98 | K6: =G6+H6+I6 -> 11832.98 | L6: =IF(K6<=2000,(0),IF(K6<=4000,(K6*0.15)-300,IF(K6<=7000,(K6*0.2)-500,IF(K6<=10000,(K6*0.25)-850,IF(K6<=14000,(K6*0.3)-1350,IF(K6>14000,(K6*0.35)-2050)))))) -> 2199.894 | M6: =F6*0.07 -> 633.0884 | N6: =G6*0.11 -> 994.8532 | P6: =L6+M6+O6 -> 2832.9824 | R6: =J6-P6+Q6 -> 8999.9976 | S6: =R6-9000 -> -0.0024
A7: Total | F7: =SUM(F6:F6) -> 9044.12 | G7: =SUM(G6:G6) -> 9044.12 | H7: =SUM(H6:H6) -> 0 | I7: =SUM(I6:I6) -> 2788.86 | J7: =SUM(J6:J6) -> 11832.98 | K7: =SUM(K6:K6) -> 11832.98 | L7: =SUM(L6:L6) -> 2199.894 | M7: =SUM(M6:M6) -> 633.0884 | ... R7: =SUM(R6:R6) -> 8999.9976
A10: Prepaired By | G10: Checked By:- | M10: Approved By:-
A11: Name :- _____________________________ | G11: Name :- ______________________________ | M11: Name :- ______________________________
A12: Sign :- ______________________________ | G12: Sign :- ________________________________ | M12: Sign :- ________________________________
A13: Date:- _____________________________ | G13: Date:- _______________________________ | M13: Date:- _______________________________

Sheet Mendida
A1: LeapFrog Software Technology Africa PLC
A2: Payroll Sheet Mendida shop
A3: For the Month of Sene 2018
A5: No. | B5: Name of Employees | C5: Position | D5: Work place | E5: Working days | F5: Basic Salary | G5: Monthly Salary | H5: Commiss. /OT | I5: KPI | J5: Gross Salary | K5: Taxable Income | L5: Income Tax | M5: Pension 7% | N5: Pension 11% | O5: Shortage/ Loan | P5: Total Deduction | Q5: Transport & other allowance | R5: Net Pay | S5: sign
A6: 1 | B6: Hailey Fantu | C6: Area SV | D6: Mendida | E6: 30 | F6: 17155.18 | G6: =+F6/30*E6 -> 17155.18 | H6: 16483 | I6: 3076.92 | J6: =G6+H6+I6 -> 36715.1 | K6: =G6+H6+I6 -> 36715.1 | L6: =IF(K6<=2000,(0),IF(K6<=4000,(K6*0.15)-300,IF(K6<=7000,(K6*0.2)-500,IF(K6<=10000,(K6*0.25)-850,IF(K6<=14000,(K6*0.3)-1350,IF(K6>14000,(K6*0.35)-2050)))))) -> 10800.285 | M6: =F6*0.07 -> 1200.8626 | N6: =F6*0.11 -> 1887.0698 | P6: =L6+M6+O6 -> 12001.148 | R6: =J6-P6+Q6 -> 24713.952
A7: Total | F7: =SUM(F6:F6) -> 17155.18 | G7: =SUM(G6:G6) -> 17155.18 | H7: =SUM(H6:H6) -> 16483 | I7: =SUM(I6:I6) -> 3076.92 | J7: =SUM(J6:J6) -> 36715.1 | K7: =SUM(K6:K6) -> 36715.1 | L7: =SUM(L6:L6) -> 10800.285 | M7: =SUM(M6:M6) -> 1200.8626 | ... R7: =SUM(R6:R6) -> 24713.952
A9: Prepaired By | G9: Checked By:- | M9: Approved By:-
A10: Name :- _____________________________ | G10: Name :- ______________________________ | M10: Name :- ______________________________
A11: Sign :- ______________________________ | G11: Sign :- ________________________________ | M11: Sign :- ________________________________
A12: Date:- _____________________________ | G12: Date:- _______________________________ | M12: Date:- _______________________________

Sheet Sendafa
A1: LeapFrog Software Technology Africa PLC
A2: Payroll Sheet Sendafa shop
A3: For the Month of Megabit 2018
A5: No. | B5: Name of Employees | C5: Position | D5: Work place | E5: Working days | F5: Basic Salary | G5: Monthly Salary | H5: Commiss. /OT | I5: KPI | J5: Gross Salary | K5: Taxable Income | L5: Income Tax | M5: Pension 7% | N5: Pension 11% | O5: Shortage/ Loan | P5: Total Deduction | Q5: Transport & other allowance | R5: Net Pay | S5: sign
A6: 1 | B6: Arsema Tariku | C6: ASM | D6: Sendafa | E6: 30 | F6: 35344.83 | G6: =+F6/30*E6 -> 35344.83 | J6: =G6+H6+I6 -> 35344.83 | K6: =G6+H6+I6 -> 35344.83 | L6: =IF(K6<=2000,(0),IF(K6<=4000,(K6*0.15)-300,IF(K6<=7000,(K6*0.2)-500,IF(K6<=10000,(K6*0.25)-850,IF(K6<=14000,(K6*0.3)-1350,IF(K6>14000,(K6*0.35)-2050)))))) -> 10320.691 | M6: =F6*0.07 -> 2474.1381 | N6: =F6*0.11 -> 3887.9313 | P6: =L6+M6+O6 -> 12794.829 | Q6: 2000 | R6: =J6-P6+Q6 -> 24550.001
A7: 2 | B7: Bekam Tadese | C7: BA Coordinator | D7: Sendafa | E7: 30 | F7: 4794.52 | G7: =+F7/30*E7 -> 4794.52 | I7: =2519.64 -> 2519.64 | J7: =G7+H7+I7 -> 7314.16 | K7: =G7+H7+I7 -> 7314.16 | L7: =IF(K7<=2000,(0),IF(K7<=4000,(K7*0.15)-300,IF(K7<=7000,(K7*0.2)-500,IF(K7<=10000,(K7*0.25)-850,IF(K7<=14000,(K7*0.3)-1350,IF(K7>14000,(K7*0.35)-2050)))))) -> 978.54 | M7: =F7*0.07 -> 335.6164 | N7: =F7*0.11 -> 527.3972 | P7: =L7+M7+O7 -> 1314.1564 | Q7: 1000 | R7: =J7-P7+Q7 -> 7000.0036
A8: 3 | B8: Dinkenesh Yadetae | C8: Cleaner | D8: Sendafa | E8: 30 | F8: 1740.39 | G8: =+F8/30*E8 -> 1740.39 | J8: =G8+H8+I8 -> 1740.39 | K8: =G8+H8+I8 -> 1740.39 | L8: =IF(K8<=2000,(0),IF(K8<=4000,(K8*0.15)-300,IF(K8<=7000,(K8*0.2)-500,IF(K8<=10000,(K8*0.25)-850,IF(K8<=14000,(K8*0.3)-1350,IF(K8>14000,(K8*0.35)-2050)))))) -> 0 | M8: =F8*0.07 -> 121.8273 | N8: =F8*0.11 -> 191.4429 | P8: =L8+M8+O8 -> 121.8273 | R8: =J8-P8+Q8 -> 1618.5627
A9: 5 | B9: Gebeyanesh Wonedemu | C9: Cleaner | D9: Sendafa Beke | E9: 30 | F9: 1740.39 | G9: =+F9/30*E9 -> 1740.39 | J9: =G9+H9+I9 -> 1740.39 | K9: =G9+H9+I9 -> 1740.39 | L9: =IF(K9<=2000,(0),IF(K9<=4000,(K9*0.15)-300,IF(K9<=7000,(K9*0.2)-500,IF(K9<=10000,(K9*0.25)-850,IF(K9<=14000,(K9*0.3)-1350,IF(K9>14000,(K9*0.35)-2050)))))) -> 0 | M9: =F9*0.07 -> 121.8273 | N9: =F9*0.11 -> 191.4429 | P9: =L9+M9+O9 -> 121.8273 | R9: =J9-P9+Q9 -> 1618.5627
A10: 6 | B10: Merawit Dendena | C10: DSP | D10: Sendafa Beke | E10: 30 | F10: 8007.94 | G10: =+F10/30*E10 -> 8007.94 | I10: =2857.14 -> 2857.14 | J10: =G10+H10+I10 -> 10865.08 | K10: =G10+H10+I10 -> 10865.08 | L10: =IF(K10<=2000,(0),IF(K10<=4000,(K10*0.15)-300,IF(K10<=7000,(K10*0.2)-500,IF(K10<=10000,(K10*0.25)-850,IF(K10<=14000,(K10*0.3)-1350,IF(K10>14000,(K10*0.35)-2050)))))) -> 1909.524 | M10: =F10*0.07 -> 560.5558 | N10: =F10*0.11 -> 880.8734 | P10: =L10+M10+O10 -> 2470.0798 | Q10: 1000 | R10: =J10-P10+Q10 -> 9395.0002
A11: 7 | B11: Mintamir Asefaw | C11: S.Accountant | D11: Sendafa | E11: 30 | F11: 10701.98 | G11: =+F11/30*E11 -> 10701.98 | I11: =2857.14 -> 2857.14 | J11: =G11+H11+I11 -> 13559.12 | K11: =G11+H11+I11 -> 13559.12 | L11: =IF(K11<=2000,(0),IF(K11<=4000,(K11*0.15)-300,IF(K11<=7000,(K11*0.2)-500,IF(K11<=10000,(K11*0.25)-850,IF(K11<=14000,(K11*0.3)-1350,IF(K11>14000,(K11*0.35)-2050)))))) -> 2717.736 | M11: =F11*0.07 -> 749.1386 | N11: =F11*0.11 -> 1177.2178 | P11: =L11+M11+O11 -> 3466.8746 | R11: =J11-P11+Q11 -> 10092.245
A12: 8 | B12: Yehalawork Tafesse | C12: Security | D12: Sendafa | E12: 30 | F12: 4380.14 | G12: =+F12/30*E12 -> 4380.14 | J12: =G12+H12+I12 -> 4380.14 | K12: =G12+H12+I12 -> 4380.14 | L12: =IF(K12<=2000,(0),IF(K12<=4000,(K12*0.15)-300,IF(K12<=7000,(K12*0.2)-500,IF(K12<=10000,(K12*0.25)-850,IF(K12<=14000,(K12*0.3)-1350,IF(K12>14000,(K12*0.35)-2050)))))) -> 376.028 | P12: =L12+M12+O12 -> 376.028 | R12: =J12-P12+Q12 -> 4004.112
A13: 9 | B13: Yismashewa Endaye | C13: DSP | D13: Sendafa | E13: 30 | F13: 7573.53 | G13: =+F13/30*E13 -> 7573.53 | I13: =2683.83/30*E13 -> 2683.83 | J13: =G13+H13+I13 -> 10257.36 | K13: =G13+H13+I13 -> 10257.36 | L13: =IF(K13<=2000,(0),IF(K13<=4000,(K13*0.15)-300,IF(K13<=7000,(K13*0.2)-500,IF(K13<=10000,(K13*0.25)-850,IF(K13<=14000,(K13*0.3)-1350,IF(K13>14000,(K13*0.35)-2050)))))) -> 1727.208 | M13: =F13*0.07 -> 530.1471 | N13: =F13*0.11 -> 833.0883 | P13: =L13+M13+O13 -> 2257.3551 | Q13: =1000/30*E13 -> 1000 | R13: =J13-P13+Q13 -> 9000.0049
A14: 10 | B14: Yonas Hussen | C14: Shop SV | D14: Sendafa | E14: 30 | F14: 17155.18 | G14: =+F14/30*E14 -> 17155.18 | J14: =G14+H14+I14 -> 17155.18 | K14: =G14+H14+I14 -> 17155.18 | L14: =IF(K14<=2000,(0),IF(K14<=4000,(K14*0.15)-300,IF(K14<=7000,(K14*0.2)-500,IF(K14<=10000,(K14*0.25)-850,IF(K14<=14000,(K14*0.3)-1350,IF(K14>14000,(K14*0.35)-2050)))))) -> 3954.313 | M14: =F14*0.07 -> 1200.8626 | N14: =F14*0.11 -> 1887.0698 | P14: =L14+M14+O14 -> 5155.1756 | Q14: 1000 | R14: =J14-P14+Q14 -> 13000.004
A15: Total | F15: =SUM(F6:F14) -> 91438.9 | G15: =SUM(G6:G14) -> 91438.9 | H15: =SUM(H6:H14) -> 0 | I15: =SUM(I6:I14) -> 10917.75 | J15: =SUM(J6:J14) -> 102356.65 | K15: =SUM(K6:K14) -> 102356.65 | L15: =SUM(L6:L14) -> 21984.039 | M15: =SUM(M6:M14) -> 6094.1132 | ... R15: =SUM(R6:R14) -> 80278.497
A18: Prepaired By | G18: Checked By:- | M18: Approved By:-
A19: Name :- _____________________________ | G19: Name :- ______________________________ | M19: Name :- ______________________________
A20: Sign :- ______________________________ | G20: Sign :- ________________________________ | M20: Sign :- ________________________________
A21: Date:- _____________________________ | G21: Date:- _______________________________ | M21: Date:- _______________________________

Sheet Sheno
A1: LeapFrog Software Technology Africa PLC
A2: Payroll Sheet Sheno shop
A3: For the Month of Megabit 2018
A5: No. | B5: Name of Employees | C5: Position | D5: Work place | E5: Working days | F5: Basic Salary | G5: Monthly Salary | H5: Commiss. /OT | I5: KPI | J5: Gross Salary | K5: Taxable Income | L5: Income Tax | M5: Pension 7% | N5: Pension 11% | O5: Shortage/ Loan | P5: Total Deduction | Q5: Transport & other allowance | R5: Net Pay | S5: sign
A6: 1 | B6: Fetene Belete | C6: Area SV | D6: Sheno | E6: 30 | F6: 17155.18 | G6: =+F6/30*E6 -> 17155.18 | H6: =4615.38 -> 4615.38 | I6: 3076.92 | J6: =G6+H6+I6 -> 24847.48 | K6: =G6+H6+I6 -> 24847.48 | L6: =IF(K6<=2000,(0),IF(K6<=4000,(K6*0.15)-300,IF(K6<=7000,(K6*0.2)-500,IF(K6<=10000,(K6*0.25)-850,IF(K6<=14000,(K6*0.3)-1350,IF(K6>14000,(K6*0.35)-2050)))))) -> 6646.618 | M6: =F6*0.07 -> 1200.8626 | N6: =F6*0.11 -> 1887.0698 | P6: =L6+M6+O6 -> 7847.4806 | Q6: 1000 | R6: =J6-P6+Q6 -> 17999.999 | S6: =R6-18000 -> -0.0006
A7: 2 | B7: Million Sime Bekele | C7: BA coordinator | D7: Sheno | E7: 30 | F7: 6164.38 | G7: =+F7/30*E7 -> 6164.38 | I7: =2610.96 -> 2610.96 | J7: =G7+H7+I7 -> 8775.34 | K7: =G7+H7+I7 -> 8775.34 | L7: =IF(K7<=2000,(0),IF(K7<=4000,(K7*0.15)-300,IF(K7<=7000,(K7*0.2)-500,IF(K7<=10000,(K7*0.25)-850,IF(K7<=14000,(K7*0.3)-1350,IF(K7>14000,(K7*0.35)-2050)))))) -> 1343.835 | M7: =F7*0.07 -> 431.5066 | N7: =F7*0.11 -> 678.0818 | P7: =L7+M7+O7 -> 1775.3416 | R7: =J7-P7+Q7 -> 6999.9984
A8: 3 | B8: Rabiya Kasahun | C8: DSP | D8: Sheno | E8: 30 | F8: 7573.53 | G8: =+F8/30*E8 -> 7573.53 | I8: =2683.83/30*E8 -> 2683.83 | J8: =G8+H8+I8 -> 10257.36 | K8: =G8+H8+I8 -> 10257.36 | L8: =IF(K8<=2000,(0),IF(K8<=4000,(K8*0.15)-300,IF(K8<=7000,(K8*0.2)-500,IF(K8<=10000,(K8*0.25)-850,IF(K8<=14000,(K8*0.3)-1350,IF(K8>14000,(K8*0.35)-2050)))))) -> 1727.208 | P8: =L8+M8+O8 -> 1727.208 | Q8: =1000/30*E8 -> 1000 | R8: =J8-P8+Q8 -> 9530.152
A9: 4 | B9: Tesfanesh Fana | C9: Cleaner | D9: Sheno | E9: 30 | F9: 2185.29 | G9: =+F9/30*E9 -> 2185.29 | J9: =G9+H9+I9 -> 2185.29 | K9: =G9+H9+I9 -> 2185.29 | L9: =IF(K9<=2000,(0),IF(K9<=4000,(K9*0.15)-300,IF(K9<=7000,(K9*0.2)-500,IF(K9<=10000,(K9*0.25)-850,IF(K9<=14000,(K9*0.3)-1350,IF(K9>14000,(K9*0.35)-2050)))))) -> 27.7935 | M9: =F9*0.07 -> 152.9703 | N9: =F9*0.11 -> 240.3819 | P9: =L9+M9+O9 -> 180.7638 | R9: =J9-P9+Q9 -> 2004.5262
A10: 5 | B10: Tizazu Tilahun | C10: Security | D10: Sheno | E10: 30 | F10: 3996.87 | G10: =+F10/30*E10 -> 3996.87 | J10: =G10+H10+I10 -> 3996.87 | K10: =G10+H10+I10 -> 3996.87 | L10: =IF(K10<=2000,(0),IF(K10<=4000,(K10*0.15)-300,IF(K10<=7000,(K10*0.2)-500,IF(K10<=10000,(K10*0.25)-850,IF(K10<=14000,(K10*0.3)-1350,IF(K10>14000,(K10*0.35)-2050)))))) -> 299.5305 | P10: =L10+M10+O10 -> 299.5305 | R10: =J10-P10+Q10 -> 3697.3395
A11: 6 | B11: Wosene Denssie | C11: S.Accountant | D11: Sheno | E11: 30 | F11: 9044.12 | G11: =+F11/30*E11 -> 9044.12 | I11: 2788.86 | J11: =G11+H11+I11 -> 11832.98 | K11: =G11+H11+I11 -> 11832.98 | L11: =IF(K11<=2000,(0),IF(K11<=4000,(K11*0.15)-300,IF(K11<=7000,(K11*0.2)-500,IF(K11<=10000,(K11*0.25)-850,IF(K11<=14000,(K11*0.3)-1350,IF(K11>14000,(K11*0.35)-2050)))))) -> 2199.894 | M11: =F11*0.07 -> 633.0884 | N11: =F11*0.11 -> 994.8532 | P11: =L11+M11+O11 -> 2832.9824 | Q11: 1000 | R11: =J11-P11+Q11 -> 9999.9976
A12: Total | F12: =SUM(F6:F11) -> 46119.37 | G12: =SUM(G6:G11) -> 46119.37 | H12: =SUM(H6:H11) -> 4615.38 | I12: =SUM(I6:I11) -> 11160.57 | J12: =SUM(J6:J11) -> 61895.32 | K12: =SUM(K6:K11) -> 61895.32 | L12: =SUM(L6:L11) -> 12244.879 | M12: =SUM(M6:M11) -> 2418.4279 | ... R12: =SUM(R6:R11) -> 50232.013
A14: Prepaired By | G14: Checked By:- | M14: Approved By:-
A15: Name :- _____________________________ | G15: Name :- ______________________________ | M15: Name :- ______________________________
A16: Sign :- ______________________________ | G16: Sign :- ________________________________ | M16: Sign :- ________________________________
A17: Date:- _____________________________ | G17: Date:- _______________________________ | M17: Date:- _______________________________

Sheet Performance Summary
A1: DSA March AIRTIME SALES PERFORMANCE
A2: No | B2: Shop | C2: DSA Name | D2: Employee Type | E2: Monthly targer | F2: Sales | G2: Per | H2: trans | I2: KPI | J2: % | K2: Commission
A3: 1 | B3: KotebeHana | C3: Solomon | D3: Old | E3: 405000 | F3: 300800 | G3: =F3/E3 -> 0.74271605 | H3: =IF(D3="New", "Yes", IF(G3>=0.4, "Yes", "No")) -> Yes | I3: =IF(D3="New", IF(G3>=0.4, "100%", ""), IF(G3>=0.6, "100%", IF(G3>=0.5, "50%", ""))) -> 100% | J3: =IF(G3>=1, "1+1.5", IF(G3>=0.8, "1", ""))
A4: 2 | B4: Kotebe Kara | C4: Sekina | D4: Old | E4: 405000 | F4: 324981 | G4: =F4/E4 -> 0.80242222 | H4: =IF(D4="New", "Yes", IF(G4>=0.4, "Yes", "No")) -> Yes | I4: =IF(D4="New", IF(G4>=0.4, "100%", ""), IF(G4>=0.6, "100%", IF(G4>=0.5, "50%", ""))) -> 100% | J4: =IF(G4>=1, "1+1.5", IF(G4>=0.8, "1", "")) -> 1 | K4: =F4*0.01 -> 3249.81
A5: 3 | B5: Bole Arabsa | C5: Lalisa | D5: Old | E5: 405000 | F5: 303366 | G5: =F5/E5 -> 0.74905185 | H5: =IF(D5="New", "Yes", IF(G5>=0.4, "Yes", "No")) -> Yes | I5: =IF(D5="New", IF(G5>=0.4, "100%", ""), IF(G5>=0.6, "100%", IF(G5>=0.5, "50%", ""))) -> 100% | J5: =IF(G5>=1, "1+1.5", IF(G5>=0.8, "1", ""))
A6: 4 | B6: Sendafa | C6: Birtukan | D6: Old | E6: 405000 | F6: 705700 | G6: =F6/E6 -> 1.7424691 | H6: =IF(D6="New", "Yes", IF(G6>=0.4, "Yes", "No")) -> Yes | I6: =IF(D6="New", IF(G6>=0.4, "100%", ""), IF(G6>=0.6, "100%", IF(G6>=0.5, "50%", ""))) -> 100% | J6: =IF(G6>=1, "1+1.5", IF(G6>=0.8, "1", "")) -> 1+1.5 | K6: =(E6*0.01)+(F6-E6)*0.015 -> 8560.5

Sheet Overtime
A3: Overtime For Megabit 2018
A4: S.No | B4: Employee Name | C4: Basic Salary | D4: Normal hours | E4: Night | F4: Sunday | G4: Hollyday | H4: Total Hrs | I4: Amount
A5: 1 | B5: Bogale Bekele | C5: 5084.07 | F5: =8*2*5 -> 80 | G5: =8*2.5*2 -> 40 | H5: =SUM(D5:G5) -> 120 | I5: =C5/208*H5 -> 2933.1173
B6: Total | H6: =SUM(D6:G6) -> 0 | I6: =SUM(I5) -> 2933.1173
